{"screenshots":["https://plugins.jetbrains.com/files/6317/screenshot_c09eb428-8b6c-4aa7-9820-dd8afecce8ab","https://plugins.jetbrains.com/files/6317/screenshot_e2fd073e-c331-49b7-8df9-db74b1ffc442"],"sourceCodeUrl":"https://github.com/mplushnikov/lombok-intellij-plugin/archive/master.zip","licenseUrl":"https://plugins.jetbrains.com/files/6317/license.txt","bugtrackerUrl":"https://youtrack.jetbrains.com/issues/IDEA?q=%23%7BFrameworks.%20Lombok%7D%20","vendor":{"name":"JetBrains s.r.o.","isTrader":true,"isVerified":true},"reportPluginUrl":"https://plugins.jetbrains.com/plugin/6317-lombok?report=plugin"}