{
  "appInfo" : {
    "build" : "241.18034.62.2411.12071903",
    "buildDate" : "2024-07-10T21:13:00Z[UTC]",
    "productCode" : "AI",
    "generated" : "2024-07-29T06:23:27.8996051Z",
    "os" : "Windows 10.0",
    "runtime" : "JetBrains s.r.o. 17.0.11 17.0.11+0--11852314"
  },
  "runtimeInfo" : {
    "maxMemory" : 2147483648,
    "numberOfProcessors" : 4,
    "maxNumberOfIndexingThreads" : 3,
    "maxSizeOfFileForIntelliSense" : 102398976,
    "maxSizeOfFileForContentLoading" : 102398976
  },
  "type" : "Scanning",
  "projectIndexingActivityHistory" : {
    "projectName" : "My Application2222",
    "times" : {
      "scanningReason" : "On project open",
      "scanningType" : "FULL_ON_PROJECT_OPEN",
      "scanningId" : 0,
      "creatingIteratorsTime" : 3545166200,
      "concurrentHandlingWallTimeWithoutPauses" : 12485178700,
      "concurrentHandlingWallTimeWithPauses" : 12485178700,
      "concurrentHandlingSumOfThreadTimesWithPauses" : 28893533200,
      "concurrentIterationAndScannersApplicationSumOfThreadTimesWithPauses" : 22830236400,
      "concurrentFileCheckSumOfThreadTimesWithPauses" : 5948865100,
      "delayedPushPropertiesStageTime" : 15622200,
      "indexExtensionsTime" : 0,
      "dumbWallTimeWithPauses" : 0,
      "dumbWallTimeWithoutPauses" : 0,
      "updatingStart" : "2024-07-29T06:23:10.7524439Z",
      "updatingEnd" : "2024-07-29T06:23:27.3080477Z",
      "totalWallTimeWithPauses" : 16549420700,
      "wallTimeOnPause" : 0,
      "wasInterrupted" : false,
      "totalWallTimeWithoutPauses" : 16549420700
    },
    "fileCount" : {
      "numberOfFileProviders" : 127,
      "numberOfScannedFiles" : 93800,
      "numberOfFilesIndexedByInfrastructureExtensionsDuringScan" : 0,
      "numberOfFilesScheduledForIndexingAfterScan" : 0
    },
    "scanningStatistics" : [ {
      "providerName" : "Module 'My_Application2222' (all roots)",
      "numberOfScannedFiles" : 1101,
      "numberOfSkippedFiles" : 0,
      "numberOfFilesForIndexing" : 0,
      "numberOfFilesFullyIndexedByInfrastructureExtensions" : 0,
      "filesFullyIndexedByInfrastructureExtensions" : [ ],
      "statusTime" : 13187300,
      "totalOneThreadTimeWithPauses" : 5018462700,
      "iterationAndScannersApplicationTime" : 4580495400,
      "filesCheckTime" : 437806300,
      "timeProcessingUpToDateFiles" : 0,
      "timeUpdatingContentLessIndexes" : 0,
      "timeIndexingWithoutContentViaInfrastructureExtension" : 0,
      "roots" : [ ]
    }, {
      "providerName" : "JDK 17 C:/Program Files/Java/jdk-17/jdk-17.0.12",
      "numberOfScannedFiles" : 41153,
      "numberOfSkippedFiles" : 0,
      "numberOfFilesForIndexing" : 0,
      "numberOfFilesFullyIndexedByInfrastructureExtensions" : 0,
      "filesFullyIndexedByInfrastructureExtensions" : [ ],
      "statusTime" : 91127400,
      "totalOneThreadTimeWithPauses" : 3463019500,
      "iterationAndScannersApplicationTime" : 3319711200,
      "filesCheckTime" : 142964400,
      "timeProcessingUpToDateFiles" : 0,
      "timeUpdatingContentLessIndexes" : 0,
      "timeIndexingWithoutContentViaInfrastructureExtension" : 0,
      "roots" : [ ]
    }, {
      "providerName" : "Library Gradle: androidx.transition:transition:1.2.0@aar (#3 class roots, #1 source roots)",
      "numberOfScannedFiles" : 200,
      "numberOfSkippedFiles" : 0,
      "numberOfFilesForIndexing" : 0,
      "numberOfFilesFullyIndexedByInfrastructureExtensions" : 0,
      "filesFullyIndexedByInfrastructureExtensions" : [ ],
      "statusTime" : 253500,
      "totalOneThreadTimeWithPauses" : 2945286100,
      "iterationAndScannersApplicationTime" : 2944529100,
      "filesCheckTime" : 563100,
      "timeProcessingUpToDateFiles" : 0,
      "timeUpdatingContentLessIndexes" : 0,
      "timeIndexingWithoutContentViaInfrastructureExtension" : 0,
      "roots" : [ ]
    }, {
      "providerName" : "Module 'My_Application2222.app.main' (all roots)",
      "numberOfScannedFiles" : 52,
      "numberOfSkippedFiles" : 0,
      "numberOfFilesForIndexing" : 0,
      "numberOfFilesFullyIndexedByInfrastructureExtensions" : 0,
      "filesFullyIndexedByInfrastructureExtensions" : [ ],
      "statusTime" : 287202700,
      "totalOneThreadTimeWithPauses" : 2858346400,
      "iterationAndScannersApplicationTime" : 2037219400,
      "filesCheckTime" : 816941700,
      "timeProcessingUpToDateFiles" : 0,
      "timeUpdatingContentLessIndexes" : 0,
      "timeIndexingWithoutContentViaInfrastructureExtension" : 0,
      "roots" : [ ]
    }, {
      "providerName" : "Library Gradle: com.google.firebase:firebase-firestore:25.0.0@aar (#2 class roots, #1 source roots)",
      "numberOfScannedFiles" : 1265,
      "numberOfSkippedFiles" : 0,
      "numberOfFilesForIndexing" : 0,
      "numberOfFilesFullyIndexedByInfrastructureExtensions" : 0,
      "filesFullyIndexedByInfrastructureExtensions" : [ ],
      "statusTime" : 1182000,
      "totalOneThreadTimeWithPauses" : 2728877500,
      "iterationAndScannersApplicationTime" : 2726582300,
      "filesCheckTime" : 2199100,
      "timeProcessingUpToDateFiles" : 0,
      "timeUpdatingContentLessIndexes" : 0,
      "timeIndexingWithoutContentViaInfrastructureExtension" : 0,
      "roots" : [ ]
    }, {
      "providerName" : "Module 'My_Application2222.app.unitTest' (all roots)",
      "numberOfScannedFiles" : 1,
      "numberOfSkippedFiles" : 0,
      "numberOfFilesForIndexing" : 0,
      "numberOfFilesFullyIndexedByInfrastructureExtensions" : 0,
      "filesFullyIndexedByInfrastructureExtensions" : [ ],
      "statusTime" : 10800,
      "totalOneThreadTimeWithPauses" : 2624616200,
      "iterationAndScannersApplicationTime" : 611922900,
      "filesCheckTime" : 2006392400,
      "timeProcessingUpToDateFiles" : 0,
      "timeUpdatingContentLessIndexes" : 0,
      "timeIndexingWithoutContentViaInfrastructureExtension" : 0,
      "roots" : [ ]
    }, {
      "providerName" : "Android SDK Android API 34, extension level 7 Platform C:/Users/gsh56/AppData/Local/Android/Sdk",
      "numberOfScannedFiles" : 24379,
      "numberOfSkippedFiles" : 0,
      "numberOfFilesForIndexing" : 0,
      "numberOfFilesFullyIndexedByInfrastructureExtensions" : 0,
      "filesFullyIndexedByInfrastructureExtensions" : [ ],
      "statusTime" : 92156200,
      "totalOneThreadTimeWithPauses" : 2163562000,
      "iterationAndScannersApplicationTime" : 1939042700,
      "filesCheckTime" : 223574800,
      "timeProcessingUpToDateFiles" : 0,
      "timeUpdatingContentLessIndexes" : 0,
      "timeIndexingWithoutContentViaInfrastructureExtension" : 0,
      "roots" : [ ]
    }, {
      "providerName" : "Module 'My_Application2222.app.androidTest' (all roots)",
      "numberOfScannedFiles" : 1,
      "numberOfSkippedFiles" : 0,
      "numberOfFilesForIndexing" : 0,
      "numberOfFilesFullyIndexedByInfrastructureExtensions" : 0,
      "filesFullyIndexedByInfrastructureExtensions" : [ ],
      "statusTime" : 16700,
      "totalOneThreadTimeWithPauses" : 1979988800,
      "iterationAndScannersApplicationTime" : 430195700,
      "filesCheckTime" : 1549260900,
      "timeProcessingUpToDateFiles" : 0,
      "timeUpdatingContentLessIndexes" : 0,
      "timeIndexingWithoutContentViaInfrastructureExtension" : 0,
      "roots" : [ ]
    }, {
      "providerName" : "Library Gradle: androidx.core:core-ktx:1.9.0@aar (#3 class roots, #1 source roots)",
      "numberOfScannedFiles" : 193,
      "numberOfSkippedFiles" : 0,
      "numberOfFilesForIndexing" : 0,
      "numberOfFilesFullyIndexedByInfrastructureExtensions" : 0,
      "filesFullyIndexedByInfrastructureExtensions" : [ ],
      "statusTime" : 162500,
      "totalOneThreadTimeWithPauses" : 1026923600,
      "iterationAndScannersApplicationTime" : 1026425200,
      "filesCheckTime" : 412200,
      "timeProcessingUpToDateFiles" : 0,
      "timeUpdatingContentLessIndexes" : 0,
      "timeIndexingWithoutContentViaInfrastructureExtension" : 0,
      "roots" : [ ]
    }, {
      "providerName" : "Library Gradle: com.google.android.gms:play-services-measurement-impl:22.0.1@aar (#2 class roots, #0 source roots)",
      "numberOfScannedFiles" : 431,
      "numberOfSkippedFiles" : 0,
      "numberOfFilesForIndexing" : 0,
      "numberOfFilesFullyIndexedByInfrastructureExtensions" : 0,
      "filesFullyIndexedByInfrastructureExtensions" : [ ],
      "statusTime" : 446700,
      "totalOneThreadTimeWithPauses" : 465914900,
      "iterationAndScannersApplicationTime" : 464957800,
      "filesCheckTime" : 862800,
      "timeProcessingUpToDateFiles" : 0,
      "timeUpdatingContentLessIndexes" : 0,
      "timeIndexingWithoutContentViaInfrastructureExtension" : 0,
      "roots" : [ ]
    }, {
      "providerName" : "Library Gradle: androidx.test.espresso:espresso-core:3.4.0@aar (#2 class roots, #1 source roots)",
      "numberOfScannedFiles" : 745,
      "numberOfSkippedFiles" : 0,
      "numberOfFilesForIndexing" : 0,
      "numberOfFilesFullyIndexedByInfrastructureExtensions" : 0,
      "filesFullyIndexedByInfrastructureExtensions" : [ ],
      "statusTime" : 49710200,
      "totalOneThreadTimeWithPauses" : 306425500,
      "iterationAndScannersApplicationTime" : 256233900,
      "filesCheckTime" : 50118800,
      "timeProcessingUpToDateFiles" : 0,
      "timeUpdatingContentLessIndexes" : 0,
      "timeIndexingWithoutContentViaInfrastructureExtension" : 0,
      "roots" : [ ]
    }, {
      "providerName" : "Library Gradle: org.jetbrains.kotlin:kotlin-stdlib-common:1.8.22 (#1 class roots, #1 source roots)",
      "numberOfScannedFiles" : 517,
      "numberOfSkippedFiles" : 0,
      "numberOfFilesForIndexing" : 0,
      "numberOfFilesFullyIndexedByInfrastructureExtensions" : 0,
      "filesFullyIndexedByInfrastructureExtensions" : [ ],
      "statusTime" : 10851900,
      "totalOneThreadTimeWithPauses" : 299049100,
      "iterationAndScannersApplicationTime" : 18888800,
      "filesCheckTime" : 280043500,
      "timeProcessingUpToDateFiles" : 0,
      "timeUpdatingContentLessIndexes" : 0,
      "timeIndexingWithoutContentViaInfrastructureExtension" : 0,
      "roots" : [ ]
    }, {
      "providerName" : "Library Gradle: com.google.firebase:protolite-well-known-types:18.0.0@aar (#2 class roots, #0 source roots)",
      "numberOfScannedFiles" : 600,
      "numberOfSkippedFiles" : 0,
      "numberOfFilesForIndexing" : 0,
      "numberOfFilesFullyIndexedByInfrastructureExtensions" : 0,
      "filesFullyIndexedByInfrastructureExtensions" : [ ],
      "statusTime" : 322000,
      "totalOneThreadTimeWithPauses" : 290633200,
      "iterationAndScannersApplicationTime" : 289871700,
      "filesCheckTime" : 596400,
      "timeProcessingUpToDateFiles" : 0,
      "timeUpdatingContentLessIndexes" : 0,
      "timeIndexingWithoutContentViaInfrastructureExtension" : 0,
      "roots" : [ ]
    }, {
      "providerName" : "Module 'My_Application2222.app' (all roots)",
      "numberOfScannedFiles" : 4,
      "numberOfSkippedFiles" : 0,
      "numberOfFilesForIndexing" : 0,
      "numberOfFilesFullyIndexedByInfrastructureExtensions" : 0,
      "filesFullyIndexedByInfrastructureExtensions" : [ ],
      "statusTime" : 38200,
      "totalOneThreadTimeWithPauses" : 290508800,
      "iterationAndScannersApplicationTime" : 289018400,
      "filesCheckTime" : 1336200,
      "timeProcessingUpToDateFiles" : 0,
      "timeUpdatingContentLessIndexes" : 0,
      "timeIndexingWithoutContentViaInfrastructureExtension" : 0,
      "roots" : [ ]
    }, {
      "providerName" : "Library Gradle: com.google.android.material:material:1.9.0@aar (#3 class roots, #1 source roots)",
      "numberOfScannedFiles" : 1898,
      "numberOfSkippedFiles" : 0,
      "numberOfFilesForIndexing" : 0,
      "numberOfFilesFullyIndexedByInfrastructureExtensions" : 0,
      "filesFullyIndexedByInfrastructureExtensions" : [ ],
      "statusTime" : 1455600,
      "totalOneThreadTimeWithPauses" : 287602600,
      "iterationAndScannersApplicationTime" : 284601300,
      "filesCheckTime" : 2898400,
      "timeProcessingUpToDateFiles" : 0,
      "timeUpdatingContentLessIndexes" : 0,
      "timeIndexingWithoutContentViaInfrastructureExtension" : 0,
      "roots" : [ ]
    }, {
      "providerName" : "Library Gradle: org.jetbrains.kotlinx:kotlinx-coroutines-android:1.7.3 (#1 class roots, #1 source roots)",
      "numberOfScannedFiles" : 28,
      "numberOfSkippedFiles" : 0,
      "numberOfFilesForIndexing" : 0,
      "numberOfFilesFullyIndexedByInfrastructureExtensions" : 0,
      "filesFullyIndexedByInfrastructureExtensions" : [ ],
      "statusTime" : 181900,
      "totalOneThreadTimeWithPauses" : 227658700,
      "iterationAndScannersApplicationTime" : 102476800,
      "filesCheckTime" : 125056800,
      "timeProcessingUpToDateFiles" : 0,
      "timeUpdatingContentLessIndexes" : 0,
      "timeIndexingWithoutContentViaInfrastructureExtension" : 0,
      "roots" : [ ]
    }, {
      "providerName" : "Library Gradle: androidx.credentials:credentials-play-services-auth:1.2.0-rc01@aar (#3 class roots, #1 source roots)",
      "numberOfScannedFiles" : 85,
      "numberOfSkippedFiles" : 0,
      "numberOfFilesForIndexing" : 0,
      "numberOfFilesFullyIndexedByInfrastructureExtensions" : 0,
      "filesFullyIndexedByInfrastructureExtensions" : [ ],
      "statusTime" : 43900,
      "totalOneThreadTimeWithPauses" : 225839100,
      "iterationAndScannersApplicationTime" : 225537900,
      "filesCheckTime" : 198800,
      "timeProcessingUpToDateFiles" : 0,
      "timeUpdatingContentLessIndexes" : 0,
      "timeIndexingWithoutContentViaInfrastructureExtension" : 0,
      "roots" : [ ]
    }, {
      "providerName" : "Library Gradle: com.google.guava:guava:31.1-android (#1 class roots, #1 source roots)",
      "numberOfScannedFiles" : 2550,
      "numberOfSkippedFiles" : 0,
      "numberOfFilesForIndexing" : 0,
      "numberOfFilesFullyIndexedByInfrastructureExtensions" : 0,
      "filesFullyIndexedByInfrastructureExtensions" : [ ],
      "statusTime" : 1371200,
      "totalOneThreadTimeWithPauses" : 186344000,
      "iterationAndScannersApplicationTime" : 183956700,
      "filesCheckTime" : 2297800,
      "timeProcessingUpToDateFiles" : 0,
      "timeUpdatingContentLessIndexes" : 0,
      "timeIndexingWithoutContentViaInfrastructureExtension" : 0,
      "roots" : [ ]
    }, {
      "providerName" : "Library Gradle: org.checkerframework:checker-qual:3.33.0 (#1 class roots, #1 source roots)",
      "numberOfScannedFiles" : 703,
      "numberOfSkippedFiles" : 0,
      "numberOfFilesForIndexing" : 0,
      "numberOfFilesFullyIndexedByInfrastructureExtensions" : 0,
      "filesFullyIndexedByInfrastructureExtensions" : [ ],
      "statusTime" : 92545700,
      "totalOneThreadTimeWithPauses" : 173199400,
      "iterationAndScannersApplicationTime" : 79408500,
      "filesCheckTime" : 93654900,
      "timeProcessingUpToDateFiles" : 0,
      "timeUpdatingContentLessIndexes" : 0,
      "timeIndexingWithoutContentViaInfrastructureExtension" : 0,
      "roots" : [ ]
    }, {
      "providerName" : "Library Gradle: junit:junit:4.13.2 (#1 class roots, #1 source roots)",
      "numberOfScannedFiles" : 578,
      "numberOfSkippedFiles" : 0,
      "numberOfFilesForIndexing" : 0,
      "numberOfFilesFullyIndexedByInfrastructureExtensions" : 0,
      "filesFullyIndexedByInfrastructureExtensions" : [ ],
      "statusTime" : 279200,
      "totalOneThreadTimeWithPauses" : 158923300,
      "iterationAndScannersApplicationTime" : 158258100,
      "filesCheckTime" : 594300,
      "timeProcessingUpToDateFiles" : 0,
      "timeUpdatingContentLessIndexes" : 0,
      "timeIndexingWithoutContentViaInfrastructureExtension" : 0,
      "roots" : [ ]
    }, {
      "providerName" : "Library Gradle: org.jetbrains.kotlin:kotlin-stdlib:1.8.22 (#1 class roots, #1 source roots)",
      "numberOfScannedFiles" : 1157,
      "numberOfSkippedFiles" : 0,
      "numberOfFilesForIndexing" : 0,
      "numberOfFilesFullyIndexedByInfrastructureExtensions" : 0,
      "filesFullyIndexedByInfrastructureExtensions" : [ ],
      "statusTime" : 663600,
      "totalOneThreadTimeWithPauses" : 134130100,
      "iterationAndScannersApplicationTime" : 132770600,
      "filesCheckTime" : 1230100,
      "timeProcessingUpToDateFiles" : 0,
      "timeUpdatingContentLessIndexes" : 0,
      "timeIndexingWithoutContentViaInfrastructureExtension" : 0,
      "roots" : [ ]
    }, {
      "providerName" : "Library Gradle: com.google.android.gms:play-services-measurement:22.0.1@aar (#2 class roots, #0 source roots)",
      "numberOfScannedFiles" : 267,
      "numberOfSkippedFiles" : 0,
      "numberOfFilesForIndexing" : 0,
      "numberOfFilesFullyIndexedByInfrastructureExtensions" : 0,
      "filesFullyIndexedByInfrastructureExtensions" : [ ],
      "statusTime" : 180000,
      "totalOneThreadTimeWithPauses" : 103813200,
      "iterationAndScannersApplicationTime" : 103320400,
      "filesCheckTime" : 415100,
      "timeProcessingUpToDateFiles" : 0,
      "timeUpdatingContentLessIndexes" : 0,
      "timeIndexingWithoutContentViaInfrastructureExtension" : 0,
      "roots" : [ ]
    }, {
      "providerName" : "Library Gradle: org.checkerframework:checker-qual:3.12.0 (#1 class roots, #1 source roots)",
      "numberOfScannedFiles" : 657,
      "numberOfSkippedFiles" : 0,
      "numberOfFilesForIndexing" : 0,
      "numberOfFilesFullyIndexedByInfrastructureExtensions" : 0,
      "filesFullyIndexedByInfrastructureExtensions" : [ ],
      "statusTime" : 2549800,
      "totalOneThreadTimeWithPauses" : 103377800,
      "iterationAndScannersApplicationTime" : 98549100,
      "filesCheckTime" : 4633600,
      "timeProcessingUpToDateFiles" : 0,
      "timeUpdatingContentLessIndexes" : 0,
      "timeIndexingWithoutContentViaInfrastructureExtension" : 0,
      "roots" : [ ]
    }, {
      "providerName" : "Library Gradle: com.google.guava:guava:32.0.1-android (#1 class roots, #1 source roots)",
      "numberOfScannedFiles" : 2543,
      "numberOfSkippedFiles" : 0,
      "numberOfFilesForIndexing" : 0,
      "numberOfFilesFullyIndexedByInfrastructureExtensions" : 0,
      "filesFullyIndexedByInfrastructureExtensions" : [ ],
      "statusTime" : 1383000,
      "totalOneThreadTimeWithPauses" : 100150000,
      "iterationAndScannersApplicationTime" : 97616300,
      "filesCheckTime" : 2401800,
      "timeProcessingUpToDateFiles" : 0,
      "timeUpdatingContentLessIndexes" : 0,
      "timeIndexingWithoutContentViaInfrastructureExtension" : 0,
      "roots" : [ ]
    }, {
      "providerName" : "Library Gradle: androidx.appcompat:appcompat:1.5.0@aar (#3 class roots, #1 source roots)",
      "numberOfScannedFiles" : 922,
      "numberOfSkippedFiles" : 0,
      "numberOfFilesForIndexing" : 0,
      "numberOfFilesFullyIndexedByInfrastructureExtensions" : 0,
      "filesFullyIndexedByInfrastructureExtensions" : [ ],
      "statusTime" : 7695500,
      "totalOneThreadTimeWithPauses" : 95745400,
      "iterationAndScannersApplicationTime" : 87418800,
      "filesCheckTime" : 8232200,
      "timeProcessingUpToDateFiles" : 0,
      "timeUpdatingContentLessIndexes" : 0,
      "timeIndexingWithoutContentViaInfrastructureExtension" : 0,
      "roots" : [ ]
    }, {
      "providerName" : "Library Gradle: com.rmtheis:tess-two:9.1.0@aar (#2 class roots, #1 source roots)",
      "numberOfScannedFiles" : 65,
      "numberOfSkippedFiles" : 0,
      "numberOfFilesForIndexing" : 0,
      "numberOfFilesFullyIndexedByInfrastructureExtensions" : 0,
      "filesFullyIndexedByInfrastructureExtensions" : [ ],
      "statusTime" : 48700,
      "totalOneThreadTimeWithPauses" : 82595700,
      "iterationAndScannersApplicationTime" : 1758700,
      "filesCheckTime" : 206200,
      "timeProcessingUpToDateFiles" : 0,
      "timeUpdatingContentLessIndexes" : 0,
      "timeIndexingWithoutContentViaInfrastructureExtension" : 0,
      "roots" : [ ]
    }, {
      "providerName" : "Library Gradle: androidx.credentials:credentials:1.2.0-rc01@aar (#3 class roots, #1 source roots)",
      "numberOfScannedFiles" : 537,
      "numberOfSkippedFiles" : 0,
      "numberOfFilesForIndexing" : 0,
      "numberOfFilesFullyIndexedByInfrastructureExtensions" : 0,
      "filesFullyIndexedByInfrastructureExtensions" : [ ],
      "statusTime" : 3063800,
      "totalOneThreadTimeWithPauses" : 73640700,
      "iterationAndScannersApplicationTime" : 70112300,
      "filesCheckTime" : 3443300,
      "timeProcessingUpToDateFiles" : 0,
      "timeUpdatingContentLessIndexes" : 0,
      "timeIndexingWithoutContentViaInfrastructureExtension" : 0,
      "roots" : [ ]
    }, {
      "providerName" : "Indexable set contributor 'com.intellij.javaee.ExternalResourcesRootsProvider@3fbf254a' (non-project)",
      "numberOfScannedFiles" : 210,
      "numberOfSkippedFiles" : 4,
      "numberOfFilesForIndexing" : 0,
      "numberOfFilesFullyIndexedByInfrastructureExtensions" : 0,
      "filesFullyIndexedByInfrastructureExtensions" : [ ],
      "statusTime" : 134300,
      "totalOneThreadTimeWithPauses" : 58235500,
      "iterationAndScannersApplicationTime" : 1265000,
      "filesCheckTime" : 56915500,
      "timeProcessingUpToDateFiles" : 0,
      "timeUpdatingContentLessIndexes" : 0,
      "timeIndexingWithoutContentViaInfrastructureExtension" : 0,
      "roots" : [ ]
    }, {
      "providerName" : "Library Gradle: com.google.j2objc:j2objc-annotations:1.3 (#1 class roots, #1 source roots)",
      "numberOfScannedFiles" : 26,
      "numberOfSkippedFiles" : 0,
      "numberOfFilesForIndexing" : 0,
      "numberOfFilesFullyIndexedByInfrastructureExtensions" : 0,
      "filesFullyIndexedByInfrastructureExtensions" : [ ],
      "statusTime" : 14600,
      "totalOneThreadTimeWithPauses" : 31740100,
      "iterationAndScannersApplicationTime" : 811500,
      "filesCheckTime" : 30802500,
      "timeProcessingUpToDateFiles" : 0,
      "timeUpdatingContentLessIndexes" : 0,
      "timeIndexingWithoutContentViaInfrastructureExtension" : 0,
      "roots" : [ ]
    }, {
      "providerName" : "Library Gradle: com.google.firebase:firebase-auth:23.0.0@aar (#2 class roots, #0 source roots)",
      "numberOfScannedFiles" : 1365,
      "numberOfSkippedFiles" : 0,
      "numberOfFilesForIndexing" : 0,
      "numberOfFilesFullyIndexedByInfrastructureExtensions" : 0,
      "filesFullyIndexedByInfrastructureExtensions" : [ ],
      "statusTime" : 904700,
      "totalOneThreadTimeWithPauses" : 31450800,
      "iterationAndScannersApplicationTime" : 29275200,
      "filesCheckTime" : 1589500,
      "timeProcessingUpToDateFiles" : 0,
      "timeUpdatingContentLessIndexes" : 0,
      "timeIndexingWithoutContentViaInfrastructureExtension" : 0,
      "roots" : [ ]
    }, {
      "providerName" : "Library Gradle: org.altbeacon:android-beacon-library:2.19.5@aar (#2 class roots, #1 source roots)",
      "numberOfScannedFiles" : 229,
      "numberOfSkippedFiles" : 0,
      "numberOfFilesForIndexing" : 0,
      "numberOfFilesFullyIndexedByInfrastructureExtensions" : 0,
      "filesFullyIndexedByInfrastructureExtensions" : [ ],
      "statusTime" : 20591500,
      "totalOneThreadTimeWithPauses" : 29501300,
      "iterationAndScannersApplicationTime" : 8630400,
      "filesCheckTime" : 20770400,
      "timeProcessingUpToDateFiles" : 0,
      "timeUpdatingContentLessIndexes" : 0,
      "timeIndexingWithoutContentViaInfrastructureExtension" : 0,
      "roots" : [ ]
    }, {
      "providerName" : "Library Gradle: androidx.privacysandbox.ads:ads-adservices-java:1.0.0-beta05@aar (#3 class roots, #1 source roots)",
      "numberOfScannedFiles" : 47,
      "numberOfSkippedFiles" : 0,
      "numberOfFilesForIndexing" : 0,
      "numberOfFilesFullyIndexedByInfrastructureExtensions" : 0,
      "filesFullyIndexedByInfrastructureExtensions" : [ ],
      "statusTime" : 23842600,
      "totalOneThreadTimeWithPauses" : 25270100,
      "iterationAndScannersApplicationTime" : 1195900,
      "filesCheckTime" : 23957600,
      "timeProcessingUpToDateFiles" : 0,
      "timeUpdatingContentLessIndexes" : 0,
      "timeIndexingWithoutContentViaInfrastructureExtension" : 0,
      "roots" : [ ]
    }, {
      "providerName" : "Library Gradle: androidx.print:print:1.0.0@aar (#2 class roots, #1 source roots)",
      "numberOfScannedFiles" : 11,
      "numberOfSkippedFiles" : 0,
      "numberOfFilesForIndexing" : 0,
      "numberOfFilesFullyIndexedByInfrastructureExtensions" : 0,
      "filesFullyIndexedByInfrastructureExtensions" : [ ],
      "statusTime" : 19200,
      "totalOneThreadTimeWithPauses" : 24835200,
      "iterationAndScannersApplicationTime" : 973800,
      "filesCheckTime" : 23726900,
      "timeProcessingUpToDateFiles" : 0,
      "timeUpdatingContentLessIndexes" : 0,
      "timeIndexingWithoutContentViaInfrastructureExtension" : 0,
      "roots" : [ ]
    }, {
      "providerName" : "Library Gradle: androidx.core:core:1.9.0@aar (#3 class roots, #1 source roots)",
      "numberOfScannedFiles" : 1192,
      "numberOfSkippedFiles" : 0,
      "numberOfFilesForIndexing" : 0,
      "numberOfFilesFullyIndexedByInfrastructureExtensions" : 0,
      "filesFullyIndexedByInfrastructureExtensions" : [ ],
      "statusTime" : 366200,
      "totalOneThreadTimeWithPauses" : 20173300,
      "iterationAndScannersApplicationTime" : 19350200,
      "filesCheckTime" : 726400,
      "timeProcessingUpToDateFiles" : 0,
      "timeUpdatingContentLessIndexes" : 0,
      "timeIndexingWithoutContentViaInfrastructureExtension" : 0,
      "roots" : [ ]
    }, {
      "providerName" : "Library Gradle: androidx.activity:activity:1.5.0@aar (#3 class roots, #1 source roots)",
      "numberOfScannedFiles" : 86,
      "numberOfSkippedFiles" : 0,
      "numberOfFilesForIndexing" : 0,
      "numberOfFilesFullyIndexedByInfrastructureExtensions" : 0,
      "filesFullyIndexedByInfrastructureExtensions" : [ ],
      "statusTime" : 58500,
      "totalOneThreadTimeWithPauses" : 18275500,
      "iterationAndScannersApplicationTime" : 17934100,
      "filesCheckTime" : 190700,
      "timeProcessingUpToDateFiles" : 0,
      "timeUpdatingContentLessIndexes" : 0,
      "timeIndexingWithoutContentViaInfrastructureExtension" : 0,
      "roots" : [ ]
    }, {
      "providerName" : "Library Gradle: androidx.test:runner:1.4.0@aar (#2 class roots, #1 source roots)",
      "numberOfScannedFiles" : 338,
      "numberOfSkippedFiles" : 0,
      "numberOfFilesForIndexing" : 0,
      "numberOfFilesFullyIndexedByInfrastructureExtensions" : 0,
      "filesFullyIndexedByInfrastructureExtensions" : [ ],
      "statusTime" : 362100,
      "totalOneThreadTimeWithPauses" : 18266000,
      "iterationAndScannersApplicationTime" : 17061000,
      "filesCheckTime" : 729600,
      "timeProcessingUpToDateFiles" : 0,
      "timeUpdatingContentLessIndexes" : 0,
      "timeIndexingWithoutContentViaInfrastructureExtension" : 0,
      "roots" : [ ]
    }, {
      "providerName" : "Library Gradle: com.google.protobuf:protobuf-javalite:3.22.3 (#1 class roots, #1 source roots)",
      "numberOfScannedFiles" : 527,
      "numberOfSkippedFiles" : 0,
      "numberOfFilesForIndexing" : 0,
      "numberOfFilesFullyIndexedByInfrastructureExtensions" : 0,
      "filesFullyIndexedByInfrastructureExtensions" : [ ],
      "statusTime" : 401600,
      "totalOneThreadTimeWithPauses" : 16893000,
      "iterationAndScannersApplicationTime" : 15966900,
      "filesCheckTime" : 836800,
      "timeProcessingUpToDateFiles" : 0,
      "timeUpdatingContentLessIndexes" : 0,
      "timeIndexingWithoutContentViaInfrastructureExtension" : 0,
      "roots" : [ ]
    }, {
      "providerName" : "Library Gradle: org.jetbrains.kotlinx:kotlinx-coroutines-core-jvm:1.7.3 (#1 class roots, #1 source roots)",
      "numberOfScannedFiles" : 1045,
      "numberOfSkippedFiles" : 0,
      "numberOfFilesForIndexing" : 0,
      "numberOfFilesFullyIndexedByInfrastructureExtensions" : 0,
      "filesFullyIndexedByInfrastructureExtensions" : [ ],
      "statusTime" : 815600,
      "totalOneThreadTimeWithPauses" : 15943000,
      "iterationAndScannersApplicationTime" : 14326700,
      "filesCheckTime" : 1522900,
      "timeProcessingUpToDateFiles" : 0,
      "timeUpdatingContentLessIndexes" : 0,
      "timeIndexingWithoutContentViaInfrastructureExtension" : 0,
      "roots" : [ ]
    }, {
      "providerName" : "Library Gradle: androidx.savedstate:savedstate:1.2.0@aar (#3 class roots, #1 source roots)",
      "numberOfScannedFiles" : 23,
      "numberOfSkippedFiles" : 0,
      "numberOfFilesForIndexing" : 0,
      "numberOfFilesFullyIndexedByInfrastructureExtensions" : 0,
      "filesFullyIndexedByInfrastructureExtensions" : [ ],
      "statusTime" : 47700,
      "totalOneThreadTimeWithPauses" : 10686200,
      "iterationAndScannersApplicationTime" : 7889900,
      "filesCheckTime" : 2689500,
      "timeProcessingUpToDateFiles" : 0,
      "timeUpdatingContentLessIndexes" : 0,
      "timeIndexingWithoutContentViaInfrastructureExtension" : 0,
      "roots" : [ ]
    }, {
      "providerName" : "Library Gradle: com.google.android.gms:play-services-base:18.0.1@aar (#3 class roots, #0 source roots)",
      "numberOfScannedFiles" : 508,
      "numberOfSkippedFiles" : 0,
      "numberOfFilesForIndexing" : 0,
      "numberOfFilesFullyIndexedByInfrastructureExtensions" : 0,
      "filesFullyIndexedByInfrastructureExtensions" : [ ],
      "statusTime" : 540200,
      "totalOneThreadTimeWithPauses" : 10606200,
      "iterationAndScannersApplicationTime" : 9253500,
      "filesCheckTime" : 1247200,
      "timeProcessingUpToDateFiles" : 0,
      "timeUpdatingContentLessIndexes" : 0,
      "timeIndexingWithoutContentViaInfrastructureExtension" : 0,
      "roots" : [ ]
    }, {
      "providerName" : "Library Gradle: androidx.fragment:fragment:1.3.6@aar (#3 class roots, #1 source roots)",
      "numberOfScannedFiles" : 193,
      "numberOfSkippedFiles" : 0,
      "numberOfFilesForIndexing" : 0,
      "numberOfFilesFullyIndexedByInfrastructureExtensions" : 0,
      "filesFullyIndexedByInfrastructureExtensions" : [ ],
      "statusTime" : 108600,
      "totalOneThreadTimeWithPauses" : 9659400,
      "iterationAndScannersApplicationTime" : 9311500,
      "filesCheckTime" : 249500,
      "timeProcessingUpToDateFiles" : 0,
      "timeUpdatingContentLessIndexes" : 0,
      "timeIndexingWithoutContentViaInfrastructureExtension" : 0,
      "roots" : [ ]
    }, {
      "providerName" : "Library Gradle: androidx.legacy:legacy-support-core-utils:1.0.0@aar (#2 class roots, #1 source roots)",
      "numberOfScannedFiles" : 5,
      "numberOfSkippedFiles" : 0,
      "numberOfFilesForIndexing" : 0,
      "numberOfFilesFullyIndexedByInfrastructureExtensions" : 0,
      "filesFullyIndexedByInfrastructureExtensions" : [ ],
      "statusTime" : 9800,
      "totalOneThreadTimeWithPauses" : 8792100,
      "iterationAndScannersApplicationTime" : 311900,
      "filesCheckTime" : 81300,
      "timeProcessingUpToDateFiles" : 0,
      "timeUpdatingContentLessIndexes" : 0,
      "timeIndexingWithoutContentViaInfrastructureExtension" : 0,
      "roots" : [ ]
    }, {
      "providerName" : "Library Gradle: com.google.android.recaptcha:recaptcha:18.4.0@aar (#2 class roots, #0 source roots)",
      "numberOfScannedFiles" : 463,
      "numberOfSkippedFiles" : 0,
      "numberOfFilesForIndexing" : 0,
      "numberOfFilesFullyIndexedByInfrastructureExtensions" : 0,
      "filesFullyIndexedByInfrastructureExtensions" : [ ],
      "statusTime" : 739700,
      "totalOneThreadTimeWithPauses" : 8393700,
      "iterationAndScannersApplicationTime" : 7323600,
      "filesCheckTime" : 969600,
      "timeProcessingUpToDateFiles" : 0,
      "timeUpdatingContentLessIndexes" : 0,
      "timeIndexingWithoutContentViaInfrastructureExtension" : 0,
      "roots" : [ ]
    }, {
      "providerName" : "Library Gradle: junit:junit:4.12 (#1 class roots, #1 source roots)",
      "numberOfScannedFiles" : 490,
      "numberOfSkippedFiles" : 0,
      "numberOfFilesForIndexing" : 0,
      "numberOfFilesFullyIndexedByInfrastructureExtensions" : 0,
      "filesFullyIndexedByInfrastructureExtensions" : [ ],
      "statusTime" : 379500,
      "totalOneThreadTimeWithPauses" : 8096000,
      "iterationAndScannersApplicationTime" : 7153100,
      "filesCheckTime" : 842600,
      "timeProcessingUpToDateFiles" : 0,
      "timeUpdatingContentLessIndexes" : 0,
      "timeIndexingWithoutContentViaInfrastructureExtension" : 0,
      "roots" : [ ]
    }, {
      "providerName" : "Library Gradle: com.google.android.gms:play-services-stats:17.0.2@aar (#2 class roots, #0 source roots)",
      "numberOfScannedFiles" : 20,
      "numberOfSkippedFiles" : 0,
      "numberOfFilesForIndexing" : 0,
      "numberOfFilesFullyIndexedByInfrastructureExtensions" : 0,
      "filesFullyIndexedByInfrastructureExtensions" : [ ],
      "statusTime" : 25400,
      "totalOneThreadTimeWithPauses" : 7418800,
      "iterationAndScannersApplicationTime" : 1786600,
      "filesCheckTime" : 5509400,
      "timeProcessingUpToDateFiles" : 0,
      "timeUpdatingContentLessIndexes" : 0,
      "timeIndexingWithoutContentViaInfrastructureExtension" : 0,
      "roots" : [ ]
    }, {
      "providerName" : "Library Gradle: com.google.android.gms:play-services-basement:18.3.0@aar (#3 class roots, #0 source roots)",
      "numberOfScannedFiles" : 406,
      "numberOfSkippedFiles" : 0,
      "numberOfFilesForIndexing" : 0,
      "numberOfFilesFullyIndexedByInfrastructureExtensions" : 0,
      "filesFullyIndexedByInfrastructureExtensions" : [ ],
      "statusTime" : 204700,
      "totalOneThreadTimeWithPauses" : 7305700,
      "iterationAndScannersApplicationTime" : 6647100,
      "filesCheckTime" : 549500,
      "timeProcessingUpToDateFiles" : 0,
      "timeUpdatingContentLessIndexes" : 0,
      "timeIndexingWithoutContentViaInfrastructureExtension" : 0,
      "roots" : [ ]
    }, {
      "providerName" : "Library Gradle: com.google.protobuf:protobuf-javalite:3.14.0 (#1 class roots, #1 source roots)",
      "numberOfScannedFiles" : 529,
      "numberOfSkippedFiles" : 0,
      "numberOfFilesForIndexing" : 0,
      "numberOfFilesFullyIndexedByInfrastructureExtensions" : 0,
      "filesFullyIndexedByInfrastructureExtensions" : [ ],
      "statusTime" : 274300,
      "totalOneThreadTimeWithPauses" : 7152400,
      "iterationAndScannersApplicationTime" : 6532200,
      "filesCheckTime" : 531200,
      "timeProcessingUpToDateFiles" : 0,
      "timeUpdatingContentLessIndexes" : 0,
      "timeIndexingWithoutContentViaInfrastructureExtension" : 0,
      "roots" : [ ]
    }, {
      "providerName" : "Library Gradle: androidx.recyclerview:recyclerview:1.2.1@aar (#3 class roots, #1 source roots)",
      "numberOfScannedFiles" : 249,
      "numberOfSkippedFiles" : 0,
      "numberOfFilesForIndexing" : 0,
      "numberOfFilesFullyIndexedByInfrastructureExtensions" : 0,
      "filesFullyIndexedByInfrastructureExtensions" : [ ],
      "statusTime" : 122800,
      "totalOneThreadTimeWithPauses" : 5582300,
      "iterationAndScannersApplicationTime" : 5209600,
      "filesCheckTime" : 283100,
      "timeProcessingUpToDateFiles" : 0,
      "timeUpdatingContentLessIndexes" : 0,
      "timeIndexingWithoutContentViaInfrastructureExtension" : 0,
      "roots" : [ ]
    }, {
      "providerName" : "Indexable set contributor 'org.jetbrains.kotlin.idea.base.indices.contributors.BuiltInsIndexableSetContributor@71cc387a' (non-project)",
      "numberOfScannedFiles" : 7,
      "numberOfSkippedFiles" : 0,
      "numberOfFilesForIndexing" : 0,
      "numberOfFilesFullyIndexedByInfrastructureExtensions" : 0,
      "filesFullyIndexedByInfrastructureExtensions" : [ ],
      "statusTime" : 4928400,
      "totalOneThreadTimeWithPauses" : 5119700,
      "iterationAndScannersApplicationTime" : 74300,
      "filesCheckTime" : 4983500,
      "timeProcessingUpToDateFiles" : 0,
      "timeUpdatingContentLessIndexes" : 0,
      "timeIndexingWithoutContentViaInfrastructureExtension" : 0,
      "roots" : [ ]
    }, {
      "providerName" : "Library Gradle: androidx.browser:browser:1.4.0@aar (#3 class roots, #1 source roots)",
      "numberOfScannedFiles" : 247,
      "numberOfSkippedFiles" : 0,
      "numberOfFilesForIndexing" : 0,
      "numberOfFilesFullyIndexedByInfrastructureExtensions" : 0,
      "filesFullyIndexedByInfrastructureExtensions" : [ ],
      "statusTime" : 162300,
      "totalOneThreadTimeWithPauses" : 4812400,
      "iterationAndScannersApplicationTime" : 4267000,
      "filesCheckTime" : 434300,
      "timeProcessingUpToDateFiles" : 0,
      "timeUpdatingContentLessIndexes" : 0,
      "timeIndexingWithoutContentViaInfrastructureExtension" : 0,
      "roots" : [ ]
    }, {
      "providerName" : "Library Gradle: androidx.constraintlayout:constraintlayout:2.1.1@aar (#3 class roots, #1 source roots)",
      "numberOfScannedFiles" : 224,
      "numberOfSkippedFiles" : 0,
      "numberOfFilesForIndexing" : 0,
      "numberOfFilesFullyIndexedByInfrastructureExtensions" : 0,
      "filesFullyIndexedByInfrastructureExtensions" : [ ],
      "statusTime" : 119100,
      "totalOneThreadTimeWithPauses" : 4726800,
      "iterationAndScannersApplicationTime" : 4362400,
      "filesCheckTime" : 270100,
      "timeProcessingUpToDateFiles" : 0,
      "timeUpdatingContentLessIndexes" : 0,
      "timeIndexingWithoutContentViaInfrastructureExtension" : 0,
      "roots" : [ ]
    }, {
      "providerName" : "Library Gradle: com.google.firebase:firebase-installations:18.0.0@aar (#2 class roots, #1 source roots)",
      "numberOfScannedFiles" : 68,
      "numberOfSkippedFiles" : 0,
      "numberOfFilesForIndexing" : 0,
      "numberOfFilesFullyIndexedByInfrastructureExtensions" : 0,
      "filesFullyIndexedByInfrastructureExtensions" : [ ],
      "statusTime" : 43300,
      "totalOneThreadTimeWithPauses" : 4439800,
      "iterationAndScannersApplicationTime" : 3712500,
      "filesCheckTime" : 286400,
      "timeProcessingUpToDateFiles" : 0,
      "timeUpdatingContentLessIndexes" : 0,
      "timeIndexingWithoutContentViaInfrastructureExtension" : 0,
      "roots" : [ ]
    }, {
      "providerName" : "Library Gradle: com.google.firebase:firebase-common:21.0.0@aar (#3 class roots, #1 source roots)",
      "numberOfScannedFiles" : 157,
      "numberOfSkippedFiles" : 0,
      "numberOfFilesForIndexing" : 0,
      "numberOfFilesFullyIndexedByInfrastructureExtensions" : 0,
      "filesFullyIndexedByInfrastructureExtensions" : [ ],
      "statusTime" : 82700,
      "totalOneThreadTimeWithPauses" : 4076100,
      "iterationAndScannersApplicationTime" : 3715900,
      "filesCheckTime" : 252600,
      "timeProcessingUpToDateFiles" : 0,
      "timeUpdatingContentLessIndexes" : 0,
      "timeIndexingWithoutContentViaInfrastructureExtension" : 0,
      "roots" : [ ]
    }, {
      "providerName" : "Library Gradle: androidx.vectordrawable:vectordrawable-animated:1.1.0@aar (#2 class roots, #1 source roots)",
      "numberOfScannedFiles" : 22,
      "numberOfSkippedFiles" : 0,
      "numberOfFilesForIndexing" : 0,
      "numberOfFilesFullyIndexedByInfrastructureExtensions" : 0,
      "filesFullyIndexedByInfrastructureExtensions" : [ ],
      "statusTime" : 18500,
      "totalOneThreadTimeWithPauses" : 3827600,
      "iterationAndScannersApplicationTime" : 3631000,
      "filesCheckTime" : 111600,
      "timeProcessingUpToDateFiles" : 0,
      "timeUpdatingContentLessIndexes" : 0,
      "timeIndexingWithoutContentViaInfrastructureExtension" : 0,
      "roots" : [ ]
    }, {
      "providerName" : "Library Gradle: com.google.android.gms:play-services-measurement-base:22.0.1@aar (#2 class roots, #0 source roots)",
      "numberOfScannedFiles" : 188,
      "numberOfSkippedFiles" : 0,
      "numberOfFilesForIndexing" : 0,
      "numberOfFilesFullyIndexedByInfrastructureExtensions" : 0,
      "filesFullyIndexedByInfrastructureExtensions" : [ ],
      "statusTime" : 108600,
      "totalOneThreadTimeWithPauses" : 3125800,
      "iterationAndScannersApplicationTime" : 2798900,
      "filesCheckTime" : 248700,
      "timeProcessingUpToDateFiles" : 0,
      "timeUpdatingContentLessIndexes" : 0,
      "timeIndexingWithoutContentViaInfrastructureExtension" : 0,
      "roots" : [ ]
    }, {
      "providerName" : "Library Gradle: androidx.annotation:annotation-jvm:1.6.0 (#1 class roots, #1 source roots)",
      "numberOfScannedFiles" : 146,
      "numberOfSkippedFiles" : 0,
      "numberOfFilesForIndexing" : 0,
      "numberOfFilesFullyIndexedByInfrastructureExtensions" : 0,
      "filesFullyIndexedByInfrastructureExtensions" : [ ],
      "statusTime" : 126900,
      "totalOneThreadTimeWithPauses" : 3112900,
      "iterationAndScannersApplicationTime" : 2713200,
      "filesCheckTime" : 304300,
      "timeProcessingUpToDateFiles" : 0,
      "timeUpdatingContentLessIndexes" : 0,
      "timeIndexingWithoutContentViaInfrastructureExtension" : 0,
      "roots" : [ ]
    }, {
      "providerName" : "Library Gradle: androidx.core:core-ktx:1.3.2@aar (#2 class roots, #1 source roots)",
      "numberOfScannedFiles" : 173,
      "numberOfSkippedFiles" : 0,
      "numberOfFilesForIndexing" : 0,
      "numberOfFilesFullyIndexedByInfrastructureExtensions" : 0,
      "filesFullyIndexedByInfrastructureExtensions" : [ ],
      "statusTime" : 93600,
      "totalOneThreadTimeWithPauses" : 3107500,
      "iterationAndScannersApplicationTime" : 2752300,
      "filesCheckTime" : 261900,
      "timeProcessingUpToDateFiles" : 0,
      "timeUpdatingContentLessIndexes" : 0,
      "timeIndexingWithoutContentViaInfrastructureExtension" : 0,
      "roots" : [ ]
    }, {
      "providerName" : "Library Gradle: androidx.test.ext:junit:1.1.3@aar (#2 class roots, #1 source roots)",
      "numberOfScannedFiles" : 11,
      "numberOfSkippedFiles" : 0,
      "numberOfFilesForIndexing" : 0,
      "numberOfFilesFullyIndexedByInfrastructureExtensions" : 0,
      "filesFullyIndexedByInfrastructureExtensions" : [ ],
      "statusTime" : 7700,
      "totalOneThreadTimeWithPauses" : 2795300,
      "iterationAndScannersApplicationTime" : 2592400,
      "filesCheckTime" : 96400,
      "timeProcessingUpToDateFiles" : 0,
      "timeUpdatingContentLessIndexes" : 0,
      "timeIndexingWithoutContentViaInfrastructureExtension" : 0,
      "roots" : [ ]
    }, {
      "providerName" : "Library Gradle: androidx.test:monitor:1.4.0@aar (#2 class roots, #1 source roots)",
      "numberOfScannedFiles" : 110,
      "numberOfSkippedFiles" : 0,
      "numberOfFilesForIndexing" : 0,
      "numberOfFilesFullyIndexedByInfrastructureExtensions" : 0,
      "filesFullyIndexedByInfrastructureExtensions" : [ ],
      "statusTime" : 61800,
      "totalOneThreadTimeWithPauses" : 2756000,
      "iterationAndScannersApplicationTime" : 2491000,
      "filesCheckTime" : 188000,
      "timeProcessingUpToDateFiles" : 0,
      "timeUpdatingContentLessIndexes" : 0,
      "timeIndexingWithoutContentViaInfrastructureExtension" : 0,
      "roots" : [ ]
    }, {
      "providerName" : "Library Gradle: androidx.test.services:storage:1.4.0@aar (#2 class roots, #1 source roots)",
      "numberOfScannedFiles" : 19,
      "numberOfSkippedFiles" : 0,
      "numberOfFilesForIndexing" : 0,
      "numberOfFilesFullyIndexedByInfrastructureExtensions" : 0,
      "filesFullyIndexedByInfrastructureExtensions" : [ ],
      "statusTime" : 207100,
      "totalOneThreadTimeWithPauses" : 2632100,
      "iterationAndScannersApplicationTime" : 1908900,
      "filesCheckTime" : 598600,
      "timeProcessingUpToDateFiles" : 0,
      "timeUpdatingContentLessIndexes" : 0,
      "timeIndexingWithoutContentViaInfrastructureExtension" : 0,
      "roots" : [ ]
    }, {
      "providerName" : "Library Gradle: com.google.errorprone:error_prone_annotations:2.26.0 (#1 class roots, #1 source roots)",
      "numberOfScannedFiles" : 62,
      "numberOfSkippedFiles" : 0,
      "numberOfFilesForIndexing" : 0,
      "numberOfFilesFullyIndexedByInfrastructureExtensions" : 0,
      "filesFullyIndexedByInfrastructureExtensions" : [ ],
      "statusTime" : 66500,
      "totalOneThreadTimeWithPauses" : 2619000,
      "iterationAndScannersApplicationTime" : 2327600,
      "filesCheckTime" : 190500,
      "timeProcessingUpToDateFiles" : 0,
      "timeUpdatingContentLessIndexes" : 0,
      "timeIndexingWithoutContentViaInfrastructureExtension" : 0,
      "roots" : [ ]
    }, {
      "providerName" : "Library Gradle: androidx.arch.core:core-runtime:2.0.0@aar (#2 class roots, #1 source roots)",
      "numberOfScannedFiles" : 12,
      "numberOfSkippedFiles" : 0,
      "numberOfFilesForIndexing" : 0,
      "numberOfFilesFullyIndexedByInfrastructureExtensions" : 0,
      "filesFullyIndexedByInfrastructureExtensions" : [ ],
      "statusTime" : 7500,
      "totalOneThreadTimeWithPauses" : 2060300,
      "iterationAndScannersApplicationTime" : 1855100,
      "filesCheckTime" : 109200,
      "timeProcessingUpToDateFiles" : 0,
      "timeUpdatingContentLessIndexes" : 0,
      "timeIndexingWithoutContentViaInfrastructureExtension" : 0,
      "roots" : [ ]
    }, {
      "providerName" : "Library Gradle: org.jetbrains:annotations:23.0.0 (#1 class roots, #1 source roots)",
      "numberOfScannedFiles" : 90,
      "numberOfSkippedFiles" : 0,
      "numberOfFilesForIndexing" : 0,
      "numberOfFilesFullyIndexedByInfrastructureExtensions" : 0,
      "filesFullyIndexedByInfrastructureExtensions" : [ ],
      "statusTime" : 58300,
      "totalOneThreadTimeWithPauses" : 2024600,
      "iterationAndScannersApplicationTime" : 1626500,
      "filesCheckTime" : 198000,
      "timeProcessingUpToDateFiles" : 0,
      "timeUpdatingContentLessIndexes" : 0,
      "timeIndexingWithoutContentViaInfrastructureExtension" : 0,
      "roots" : [ ]
    }, {
      "providerName" : "Library Gradle: androidx.privacysandbox.ads:ads-adservices:1.0.0-beta05@aar (#3 class roots, #1 source roots)",
      "numberOfScannedFiles" : 92,
      "numberOfSkippedFiles" : 0,
      "numberOfFilesForIndexing" : 0,
      "numberOfFilesFullyIndexedByInfrastructureExtensions" : 0,
      "filesFullyIndexedByInfrastructureExtensions" : [ ],
      "statusTime" : 45300,
      "totalOneThreadTimeWithPauses" : 1905400,
      "iterationAndScannersApplicationTime" : 1632700,
      "filesCheckTime" : 188500,
      "timeProcessingUpToDateFiles" : 0,
      "timeUpdatingContentLessIndexes" : 0,
      "timeIndexingWithoutContentViaInfrastructureExtension" : 0,
      "roots" : [ ]
    }, {
      "providerName" : "Library Gradle: androidx.viewpager2:viewpager2:1.0.0@aar (#3 class roots, #1 source roots)",
      "numberOfScannedFiles" : 60,
      "numberOfSkippedFiles" : 0,
      "numberOfFilesForIndexing" : 0,
      "numberOfFilesFullyIndexedByInfrastructureExtensions" : 0,
      "filesFullyIndexedByInfrastructureExtensions" : [ ],
      "statusTime" : 58600,
      "totalOneThreadTimeWithPauses" : 1803300,
      "iterationAndScannersApplicationTime" : 1488800,
      "filesCheckTime" : 207900,
      "timeProcessingUpToDateFiles" : 0,
      "timeUpdatingContentLessIndexes" : 0,
      "timeIndexingWithoutContentViaInfrastructureExtension" : 0,
      "roots" : [ ]
    }, {
      "providerName" : "Library Gradle: com.google.android.play:integrity:1.2.0@aar (#2 class roots, #0 source roots)",
      "numberOfScannedFiles" : 116,
      "numberOfSkippedFiles" : 0,
      "numberOfFilesForIndexing" : 0,
      "numberOfFilesFullyIndexedByInfrastructureExtensions" : 0,
      "filesFullyIndexedByInfrastructureExtensions" : [ ],
      "statusTime" : 60900,
      "totalOneThreadTimeWithPauses" : 1784700,
      "iterationAndScannersApplicationTime" : 1501400,
      "filesCheckTime" : 182600,
      "timeProcessingUpToDateFiles" : 0,
      "timeUpdatingContentLessIndexes" : 0,
      "timeIndexingWithoutContentViaInfrastructureExtension" : 0,
      "roots" : [ ]
    }, {
      "providerName" : "Library Gradle: com.google.android.gms:play-services-auth-api-phone:18.0.2@aar (#2 class roots, #0 source roots)",
      "numberOfScannedFiles" : 41,
      "numberOfSkippedFiles" : 0,
      "numberOfFilesForIndexing" : 0,
      "numberOfFilesFullyIndexedByInfrastructureExtensions" : 0,
      "filesFullyIndexedByInfrastructureExtensions" : [ ],
      "statusTime" : 22200,
      "totalOneThreadTimeWithPauses" : 1760400,
      "iterationAndScannersApplicationTime" : 1119600,
      "filesCheckTime" : 525100,
      "timeProcessingUpToDateFiles" : 0,
      "timeUpdatingContentLessIndexes" : 0,
      "timeIndexingWithoutContentViaInfrastructureExtension" : 0,
      "roots" : [ ]
    }, {
      "providerName" : "Library Gradle: androidx.lifecycle:lifecycle-livedata-core:2.5.0@aar (#3 class roots, #1 source roots)",
      "numberOfScannedFiles" : 14,
      "numberOfSkippedFiles" : 0,
      "numberOfFilesForIndexing" : 0,
      "numberOfFilesFullyIndexedByInfrastructureExtensions" : 0,
      "filesFullyIndexedByInfrastructureExtensions" : [ ],
      "statusTime" : 5400,
      "totalOneThreadTimeWithPauses" : 1681800,
      "iterationAndScannersApplicationTime" : 1424200,
      "filesCheckTime" : 120400,
      "timeProcessingUpToDateFiles" : 0,
      "timeUpdatingContentLessIndexes" : 0,
      "timeIndexingWithoutContentViaInfrastructureExtension" : 0,
      "roots" : [ ]
    }, {
      "providerName" : "Library Gradle: com.google.code.findbugs:jsr305:3.0.2 (#1 class roots, #1 source roots)",
      "numberOfScannedFiles" : 70,
      "numberOfSkippedFiles" : 0,
      "numberOfFilesForIndexing" : 0,
      "numberOfFilesFullyIndexedByInfrastructureExtensions" : 0,
      "filesFullyIndexedByInfrastructureExtensions" : [ ],
      "statusTime" : 64700,
      "totalOneThreadTimeWithPauses" : 1526100,
      "iterationAndScannersApplicationTime" : 1212200,
      "filesCheckTime" : 216900,
      "timeProcessingUpToDateFiles" : 0,
      "timeUpdatingContentLessIndexes" : 0,
      "timeIndexingWithoutContentViaInfrastructureExtension" : 0,
      "roots" : [ ]
    }, {
      "providerName" : "Library Gradle: org.hamcrest:hamcrest-core:1.3 (#1 class roots, #1 source roots)",
      "numberOfScannedFiles" : 88,
      "numberOfSkippedFiles" : 0,
      "numberOfFilesForIndexing" : 0,
      "numberOfFilesFullyIndexedByInfrastructureExtensions" : 0,
      "filesFullyIndexedByInfrastructureExtensions" : [ ],
      "statusTime" : 42800,
      "totalOneThreadTimeWithPauses" : 1519100,
      "iterationAndScannersApplicationTime" : 1278800,
      "filesCheckTime" : 142700,
      "timeProcessingUpToDateFiles" : 0,
      "timeUpdatingContentLessIndexes" : 0,
      "timeIndexingWithoutContentViaInfrastructureExtension" : 0,
      "roots" : [ ]
    }, {
      "providerName" : "Library Gradle: androidx.appcompat:appcompat-resources:1.5.0@aar (#3 class roots, #1 source roots)",
      "numberOfScannedFiles" : 55,
      "numberOfSkippedFiles" : 0,
      "numberOfFilesForIndexing" : 0,
      "numberOfFilesFullyIndexedByInfrastructureExtensions" : 0,
      "filesFullyIndexedByInfrastructureExtensions" : [ ],
      "statusTime" : 25200,
      "totalOneThreadTimeWithPauses" : 1468300,
      "iterationAndScannersApplicationTime" : 1322000,
      "filesCheckTime" : 92500,
      "timeProcessingUpToDateFiles" : 0,
      "timeUpdatingContentLessIndexes" : 0,
      "timeIndexingWithoutContentViaInfrastructureExtension" : 0,
      "roots" : [ ]
    }, {
      "providerName" : "Library Gradle: org.hamcrest:hamcrest-library:1.3 (#1 class roots, #1 source roots)",
      "numberOfScannedFiles" : 73,
      "numberOfSkippedFiles" : 0,
      "numberOfFilesForIndexing" : 0,
      "numberOfFilesFullyIndexedByInfrastructureExtensions" : 0,
      "filesFullyIndexedByInfrastructureExtensions" : [ ],
      "statusTime" : 35000,
      "totalOneThreadTimeWithPauses" : 1424700,
      "iterationAndScannersApplicationTime" : 1176900,
      "filesCheckTime" : 140900,
      "timeProcessingUpToDateFiles" : 0,
      "timeUpdatingContentLessIndexes" : 0,
      "timeIndexingWithoutContentViaInfrastructureExtension" : 0,
      "roots" : [ ]
    }, {
      "providerName" : "Library Gradle: androidx.test:core:1.4.0@aar (#2 class roots, #1 source roots)",
      "numberOfScannedFiles" : 43,
      "numberOfSkippedFiles" : 0,
      "numberOfFilesForIndexing" : 0,
      "numberOfFilesFullyIndexedByInfrastructureExtensions" : 0,
      "filesFullyIndexedByInfrastructureExtensions" : [ ],
      "statusTime" : 29900,
      "totalOneThreadTimeWithPauses" : 1419000,
      "iterationAndScannersApplicationTime" : 1182100,
      "filesCheckTime" : 145300,
      "timeProcessingUpToDateFiles" : 0,
      "timeUpdatingContentLessIndexes" : 0,
      "timeIndexingWithoutContentViaInfrastructureExtension" : 0,
      "roots" : [ ]
    }, {
      "providerName" : "Library Gradle: androidx.dynamicanimation:dynamicanimation:1.0.0@aar (#2 class roots, #1 source roots)",
      "numberOfScannedFiles" : 47,
      "numberOfSkippedFiles" : 0,
      "numberOfFilesForIndexing" : 0,
      "numberOfFilesFullyIndexedByInfrastructureExtensions" : 0,
      "filesFullyIndexedByInfrastructureExtensions" : [ ],
      "statusTime" : 51400,
      "totalOneThreadTimeWithPauses" : 1386800,
      "iterationAndScannersApplicationTime" : 1040900,
      "filesCheckTime" : 188200,
      "timeProcessingUpToDateFiles" : 0,
      "timeUpdatingContentLessIndexes" : 0,
      "timeIndexingWithoutContentViaInfrastructureExtension" : 0,
      "roots" : [ ]
    }, {
      "providerName" : "Library Gradle: com.google.android.gms:play-services-measurement-api:22.0.1@aar (#3 class roots, #0 source roots)",
      "numberOfScannedFiles" : 35,
      "numberOfSkippedFiles" : 0,
      "numberOfFilesForIndexing" : 0,
      "numberOfFilesFullyIndexedByInfrastructureExtensions" : 0,
      "filesFullyIndexedByInfrastructureExtensions" : [ ],
      "statusTime" : 71000,
      "totalOneThreadTimeWithPauses" : 1377100,
      "iterationAndScannersApplicationTime" : 1076700,
      "filesCheckTime" : 181500,
      "timeProcessingUpToDateFiles" : 0,
      "timeUpdatingContentLessIndexes" : 0,
      "timeIndexingWithoutContentViaInfrastructureExtension" : 0,
      "roots" : [ ]
    }, {
      "providerName" : "Library Gradle: com.google.firebase:firebase-components:18.0.0@aar (#2 class roots, #1 source roots)",
      "numberOfScannedFiles" : 75,
      "numberOfSkippedFiles" : 0,
      "numberOfFilesForIndexing" : 0,
      "numberOfFilesFullyIndexedByInfrastructureExtensions" : 0,
      "filesFullyIndexedByInfrastructureExtensions" : [ ],
      "statusTime" : 37600,
      "totalOneThreadTimeWithPauses" : 1363700,
      "iterationAndScannersApplicationTime" : 1115300,
      "filesCheckTime" : 138400,
      "timeProcessingUpToDateFiles" : 0,
      "timeUpdatingContentLessIndexes" : 0,
      "timeIndexingWithoutContentViaInfrastructureExtension" : 0,
      "roots" : [ ]
    }, {
      "providerName" : "Library Gradle: androidx.lifecycle:lifecycle-viewmodel:2.5.0@aar (#3 class roots, #1 source roots)",
      "numberOfScannedFiles" : 45,
      "numberOfSkippedFiles" : 0,
      "numberOfFilesForIndexing" : 0,
      "numberOfFilesFullyIndexedByInfrastructureExtensions" : 0,
      "filesFullyIndexedByInfrastructureExtensions" : [ ],
      "statusTime" : 23100,
      "totalOneThreadTimeWithPauses" : 1291200,
      "iterationAndScannersApplicationTime" : 985800,
      "filesCheckTime" : 73000,
      "timeProcessingUpToDateFiles" : 0,
      "timeUpdatingContentLessIndexes" : 0,
      "timeIndexingWithoutContentViaInfrastructureExtension" : 0,
      "roots" : [ ]
    }, {
      "providerName" : "Library Gradle: com.google.android.gms:play-services-measurement-sdk-api:22.0.1@aar (#2 class roots, #0 source roots)",
      "numberOfScannedFiles" : 56,
      "numberOfSkippedFiles" : 0,
      "numberOfFilesForIndexing" : 0,
      "numberOfFilesFullyIndexedByInfrastructureExtensions" : 0,
      "filesFullyIndexedByInfrastructureExtensions" : [ ],
      "statusTime" : 26900,
      "totalOneThreadTimeWithPauses" : 1229700,
      "iterationAndScannersApplicationTime" : 867300,
      "filesCheckTime" : 269100,
      "timeProcessingUpToDateFiles" : 0,
      "timeUpdatingContentLessIndexes" : 0,
      "timeIndexingWithoutContentViaInfrastructureExtension" : 0,
      "roots" : [ ]
    }, {
      "providerName" : "Library Gradle: com.google.errorprone:error_prone_annotations:2.11.0 (#1 class roots, #1 source roots)",
      "numberOfScannedFiles" : 58,
      "numberOfSkippedFiles" : 0,
      "numberOfFilesForIndexing" : 0,
      "numberOfFilesFullyIndexedByInfrastructureExtensions" : 0,
      "filesFullyIndexedByInfrastructureExtensions" : [ ],
      "statusTime" : 22800,
      "totalOneThreadTimeWithPauses" : 1226500,
      "iterationAndScannersApplicationTime" : 1081000,
      "filesCheckTime" : 88800,
      "timeProcessingUpToDateFiles" : 0,
      "timeUpdatingContentLessIndexes" : 0,
      "timeIndexingWithoutContentViaInfrastructureExtension" : 0,
      "roots" : [ ]
    }, {
      "providerName" : "Library Gradle: com.google.android.gms:play-services-measurement-sdk:22.0.1@aar (#2 class roots, #0 source roots)",
      "numberOfScannedFiles" : 12,
      "numberOfSkippedFiles" : 0,
      "numberOfFilesForIndexing" : 0,
      "numberOfFilesFullyIndexedByInfrastructureExtensions" : 0,
      "filesFullyIndexedByInfrastructureExtensions" : [ ],
      "statusTime" : 11800,
      "totalOneThreadTimeWithPauses" : 1216300,
      "iterationAndScannersApplicationTime" : 946600,
      "filesCheckTime" : 163100,
      "timeProcessingUpToDateFiles" : 0,
      "timeUpdatingContentLessIndexes" : 0,
      "timeIndexingWithoutContentViaInfrastructureExtension" : 0,
      "roots" : [ ]
    }, {
      "providerName" : "Library Gradle: com.google.android.gms:play-services-tasks:18.1.0@aar (#2 class roots, #0 source roots)",
      "numberOfScannedFiles" : 52,
      "numberOfSkippedFiles" : 0,
      "numberOfFilesForIndexing" : 0,
      "numberOfFilesFullyIndexedByInfrastructureExtensions" : 0,
      "filesFullyIndexedByInfrastructureExtensions" : [ ],
      "statusTime" : 32400,
      "totalOneThreadTimeWithPauses" : 1155400,
      "iterationAndScannersApplicationTime" : 927600,
      "filesCheckTime" : 121500,
      "timeProcessingUpToDateFiles" : 0,
      "timeUpdatingContentLessIndexes" : 0,
      "timeIndexingWithoutContentViaInfrastructureExtension" : 0,
      "roots" : [ ]
    }, {
      "providerName" : "Library Gradle: com.google.android.gms:play-services-ads-identifier:18.0.0@aar (#2 class roots, #0 source roots)",
      "numberOfScannedFiles" : 17,
      "numberOfSkippedFiles" : 0,
      "numberOfFilesForIndexing" : 0,
      "numberOfFilesFullyIndexedByInfrastructureExtensions" : 0,
      "filesFullyIndexedByInfrastructureExtensions" : [ ],
      "statusTime" : 8400,
      "totalOneThreadTimeWithPauses" : 1035500,
      "iterationAndScannersApplicationTime" : 780000,
      "filesCheckTime" : 101500,
      "timeProcessingUpToDateFiles" : 0,
      "timeUpdatingContentLessIndexes" : 0,
      "timeIndexingWithoutContentViaInfrastructureExtension" : 0,
      "roots" : [ ]
    }, {
      "providerName" : "Library Gradle: androidx.versionedparcelable:versionedparcelable:1.1.1@aar (#2 class roots, #1 source roots)",
      "numberOfScannedFiles" : 28,
      "numberOfSkippedFiles" : 0,
      "numberOfFilesForIndexing" : 0,
      "numberOfFilesFullyIndexedByInfrastructureExtensions" : 0,
      "filesFullyIndexedByInfrastructureExtensions" : [ ],
      "statusTime" : 12400,
      "totalOneThreadTimeWithPauses" : 1003800,
      "iterationAndScannersApplicationTime" : 682500,
      "filesCheckTime" : 207100,
      "timeProcessingUpToDateFiles" : 0,
      "timeUpdatingContentLessIndexes" : 0,
      "timeIndexingWithoutContentViaInfrastructureExtension" : 0,
      "roots" : [ ]
    }, {
      "providerName" : "Library Gradle: androidx.lifecycle:lifecycle-common:2.5.0 (#1 class roots, #1 source roots)",
      "numberOfScannedFiles" : 41,
      "numberOfSkippedFiles" : 0,
      "numberOfFilesForIndexing" : 0,
      "numberOfFilesFullyIndexedByInfrastructureExtensions" : 0,
      "filesFullyIndexedByInfrastructureExtensions" : [ ],
      "statusTime" : 31800,
      "totalOneThreadTimeWithPauses" : 966400,
      "iterationAndScannersApplicationTime" : 723500,
      "filesCheckTime" : 131500,
      "timeProcessingUpToDateFiles" : 0,
      "timeUpdatingContentLessIndexes" : 0,
      "timeIndexingWithoutContentViaInfrastructureExtension" : 0,
      "roots" : [ ]
    }, {
      "providerName" : "Library Gradle: com.google.firebase:firebase-database-collection:18.0.1@aar (#2 class roots, #1 source roots)",
      "numberOfScannedFiles" : 40,
      "numberOfSkippedFiles" : 0,
      "numberOfFilesForIndexing" : 0,
      "numberOfFilesFullyIndexedByInfrastructureExtensions" : 0,
      "filesFullyIndexedByInfrastructureExtensions" : [ ],
      "statusTime" : 22300,
      "totalOneThreadTimeWithPauses" : 957800,
      "iterationAndScannersApplicationTime" : 802500,
      "filesCheckTime" : 106900,
      "timeProcessingUpToDateFiles" : 0,
      "timeUpdatingContentLessIndexes" : 0,
      "timeIndexingWithoutContentViaInfrastructureExtension" : 0,
      "roots" : [ ]
    }, {
      "providerName" : "Library Gradle: androidx.cardview:cardview:1.0.0@aar (#3 class roots, #1 source roots)",
      "numberOfScannedFiles" : 25,
      "numberOfSkippedFiles" : 0,
      "numberOfFilesForIndexing" : 0,
      "numberOfFilesFullyIndexedByInfrastructureExtensions" : 0,
      "filesFullyIndexedByInfrastructureExtensions" : [ ],
      "statusTime" : 21000,
      "totalOneThreadTimeWithPauses" : 828000,
      "iterationAndScannersApplicationTime" : 631300,
      "filesCheckTime" : 105200,
      "timeProcessingUpToDateFiles" : 0,
      "timeUpdatingContentLessIndexes" : 0,
      "timeIndexingWithoutContentViaInfrastructureExtension" : 0,
      "roots" : [ ]
    }, {
      "providerName" : "Library Gradle: androidx.lifecycle:lifecycle-viewmodel-savedstate:2.5.0@aar (#3 class roots, #1 source roots)",
      "numberOfScannedFiles" : 30,
      "numberOfSkippedFiles" : 0,
      "numberOfFilesForIndexing" : 0,
      "numberOfFilesFullyIndexedByInfrastructureExtensions" : 0,
      "filesFullyIndexedByInfrastructureExtensions" : [ ],
      "statusTime" : 34500,
      "totalOneThreadTimeWithPauses" : 826300,
      "iterationAndScannersApplicationTime" : 604100,
      "filesCheckTime" : 145800,
      "timeProcessingUpToDateFiles" : 0,
      "timeUpdatingContentLessIndexes" : 0,
      "timeIndexingWithoutContentViaInfrastructureExtension" : 0,
      "roots" : [ ]
    }, {
      "providerName" : "Library Gradle: com.google.guava:failureaccess:1.0.1 (#1 class roots, #1 source roots)",
      "numberOfScannedFiles" : 8,
      "numberOfSkippedFiles" : 0,
      "numberOfFilesForIndexing" : 0,
      "numberOfFilesFullyIndexedByInfrastructureExtensions" : 0,
      "filesFullyIndexedByInfrastructureExtensions" : [ ],
      "statusTime" : 3100,
      "totalOneThreadTimeWithPauses" : 825500,
      "iterationAndScannersApplicationTime" : 632700,
      "filesCheckTime" : 91000,
      "timeProcessingUpToDateFiles" : 0,
      "timeUpdatingContentLessIndexes" : 0,
      "timeIndexingWithoutContentViaInfrastructureExtension" : 0,
      "roots" : [ ]
    }, {
      "providerName" : "Library Gradle: com.google.firebase:firebase-installations-interop:17.1.1@aar (#2 class roots, #1 source roots)",
      "numberOfScannedFiles" : 16,
      "numberOfSkippedFiles" : 0,
      "numberOfFilesForIndexing" : 0,
      "numberOfFilesFullyIndexedByInfrastructureExtensions" : 0,
      "filesFullyIndexedByInfrastructureExtensions" : [ ],
      "statusTime" : 7700,
      "totalOneThreadTimeWithPauses" : 814900,
      "iterationAndScannersApplicationTime" : 615400,
      "filesCheckTime" : 91500,
      "timeProcessingUpToDateFiles" : 0,
      "timeUpdatingContentLessIndexes" : 0,
      "timeIndexingWithoutContentViaInfrastructureExtension" : 0,
      "roots" : [ ]
    }, {
      "providerName" : "Library Gradle: androidx.annotation:annotation-experimental:1.3.0@aar (#3 class roots, #1 source roots)",
      "numberOfScannedFiles" : 15,
      "numberOfSkippedFiles" : 0,
      "numberOfFilesForIndexing" : 0,
      "numberOfFilesFullyIndexedByInfrastructureExtensions" : 0,
      "filesFullyIndexedByInfrastructureExtensions" : [ ],
      "statusTime" : 12900,
      "totalOneThreadTimeWithPauses" : 812500,
      "iterationAndScannersApplicationTime" : 621100,
      "filesCheckTime" : 101600,
      "timeProcessingUpToDateFiles" : 0,
      "timeUpdatingContentLessIndexes" : 0,
      "timeIndexingWithoutContentViaInfrastructureExtension" : 0,
      "roots" : [ ]
    }, {
      "providerName" : "Library Gradle: androidx.collection:collection:1.1.0 (#1 class roots, #1 source roots)",
      "numberOfScannedFiles" : 29,
      "numberOfSkippedFiles" : 0,
      "numberOfFilesForIndexing" : 0,
      "numberOfFilesFullyIndexedByInfrastructureExtensions" : 0,
      "filesFullyIndexedByInfrastructureExtensions" : [ ],
      "statusTime" : 23300,
      "totalOneThreadTimeWithPauses" : 794700,
      "iterationAndScannersApplicationTime" : 599400,
      "filesCheckTime" : 109200,
      "timeProcessingUpToDateFiles" : 0,
      "timeUpdatingContentLessIndexes" : 0,
      "timeIndexingWithoutContentViaInfrastructureExtension" : 0,
      "roots" : [ ]
    }, {
      "providerName" : "Library Gradle: androidx.viewpager:viewpager:1.0.0@aar (#2 class roots, #1 source roots)",
      "numberOfScannedFiles" : 31,
      "numberOfSkippedFiles" : 0,
      "numberOfFilesForIndexing" : 0,
      "numberOfFilesFullyIndexedByInfrastructureExtensions" : 0,
      "filesFullyIndexedByInfrastructureExtensions" : [ ],
      "statusTime" : 18700,
      "totalOneThreadTimeWithPauses" : 786600,
      "iterationAndScannersApplicationTime" : 582200,
      "filesCheckTime" : 98000,
      "timeProcessingUpToDateFiles" : 0,
      "timeUpdatingContentLessIndexes" : 0,
      "timeIndexingWithoutContentViaInfrastructureExtension" : 0,
      "roots" : [ ]
    }, {
      "providerName" : "Library Gradle: androidx.loader:loader:1.0.0@aar (#2 class roots, #1 source roots)",
      "numberOfScannedFiles" : 32,
      "numberOfSkippedFiles" : 0,
      "numberOfFilesForIndexing" : 0,
      "numberOfFilesFullyIndexedByInfrastructureExtensions" : 0,
      "filesFullyIndexedByInfrastructureExtensions" : [ ],
      "statusTime" : 20700,
      "totalOneThreadTimeWithPauses" : 754500,
      "iterationAndScannersApplicationTime" : 567900,
      "filesCheckTime" : 95200,
      "timeProcessingUpToDateFiles" : 0,
      "timeUpdatingContentLessIndexes" : 0,
      "timeIndexingWithoutContentViaInfrastructureExtension" : 0,
      "roots" : [ ]
    }, {
      "providerName" : "Library Gradle: androidx.cursoradapter:cursoradapter:1.0.0@aar (#2 class roots, #1 source roots)",
      "numberOfScannedFiles" : 16,
      "numberOfSkippedFiles" : 0,
      "numberOfFilesForIndexing" : 0,
      "numberOfFilesFullyIndexedByInfrastructureExtensions" : 0,
      "filesFullyIndexedByInfrastructureExtensions" : [ ],
      "statusTime" : 21500,
      "totalOneThreadTimeWithPauses" : 736200,
      "iterationAndScannersApplicationTime" : 529700,
      "filesCheckTime" : 106300,
      "timeProcessingUpToDateFiles" : 0,
      "timeUpdatingContentLessIndexes" : 0,
      "timeIndexingWithoutContentViaInfrastructureExtension" : 0,
      "roots" : [ ]
    }, {
      "providerName" : "Library Gradle: androidx.drawerlayout:drawerlayout:1.1.1@aar (#3 class roots, #1 source roots)",
      "numberOfScannedFiles" : 17,
      "numberOfSkippedFiles" : 0,
      "numberOfFilesForIndexing" : 0,
      "numberOfFilesFullyIndexedByInfrastructureExtensions" : 0,
      "filesFullyIndexedByInfrastructureExtensions" : [ ],
      "statusTime" : 17400,
      "totalOneThreadTimeWithPauses" : 724500,
      "iterationAndScannersApplicationTime" : 521900,
      "filesCheckTime" : 113500,
      "timeProcessingUpToDateFiles" : 0,
      "timeUpdatingContentLessIndexes" : 0,
      "timeIndexingWithoutContentViaInfrastructureExtension" : 0,
      "roots" : [ ]
    }, {
      "providerName" : "Library Gradle: com.google.j2objc:j2objc-annotations:2.8 (#1 class roots, #1 source roots)",
      "numberOfScannedFiles" : 28,
      "numberOfSkippedFiles" : 0,
      "numberOfFilesForIndexing" : 0,
      "numberOfFilesFullyIndexedByInfrastructureExtensions" : 0,
      "filesFullyIndexedByInfrastructureExtensions" : [ ],
      "statusTime" : 14500,
      "totalOneThreadTimeWithPauses" : 712100,
      "iterationAndScannersApplicationTime" : 541800,
      "filesCheckTime" : 103500,
      "timeProcessingUpToDateFiles" : 0,
      "timeUpdatingContentLessIndexes" : 0,
      "timeIndexingWithoutContentViaInfrastructureExtension" : 0,
      "roots" : [ ]
    }, {
      "providerName" : "Library Gradle: com.google.firebase:firebase-common-ktx:21.0.0@aar (#2 class roots, #1 source roots)",
      "numberOfScannedFiles" : 8,
      "numberOfSkippedFiles" : 0,
      "numberOfFilesForIndexing" : 0,
      "numberOfFilesFullyIndexedByInfrastructureExtensions" : 0,
      "filesFullyIndexedByInfrastructureExtensions" : [ ],
      "statusTime" : 5700,
      "totalOneThreadTimeWithPauses" : 697800,
      "iterationAndScannersApplicationTime" : 502000,
      "filesCheckTime" : 95500,
      "timeProcessingUpToDateFiles" : 0,
      "timeUpdatingContentLessIndexes" : 0,
      "timeIndexingWithoutContentViaInfrastructureExtension" : 0,
      "roots" : [ ]
    }, {
      "providerName" : "Library Gradle: androidx.customview:customview:1.1.0@aar (#2 class roots, #1 source roots)",
      "numberOfScannedFiles" : 24,
      "numberOfSkippedFiles" : 0,
      "numberOfFilesForIndexing" : 0,
      "numberOfFilesFullyIndexedByInfrastructureExtensions" : 0,
      "filesFullyIndexedByInfrastructureExtensions" : [ ],
      "statusTime" : 15800,
      "totalOneThreadTimeWithPauses" : 695200,
      "iterationAndScannersApplicationTime" : 528700,
      "filesCheckTime" : 81600,
      "timeProcessingUpToDateFiles" : 0,
      "timeUpdatingContentLessIndexes" : 0,
      "timeIndexingWithoutContentViaInfrastructureExtension" : 0,
      "roots" : [ ]
    }, {
      "providerName" : "Library Gradle: androidx.arch.core:core-common:2.1.0 (#1 class roots, #1 source roots)",
      "numberOfScannedFiles" : 14,
      "numberOfSkippedFiles" : 0,
      "numberOfFilesForIndexing" : 0,
      "numberOfFilesFullyIndexedByInfrastructureExtensions" : 0,
      "filesFullyIndexedByInfrastructureExtensions" : [ ],
      "statusTime" : 10000,
      "totalOneThreadTimeWithPauses" : 684000,
      "iterationAndScannersApplicationTime" : 514800,
      "filesCheckTime" : 80800,
      "timeProcessingUpToDateFiles" : 0,
      "timeUpdatingContentLessIndexes" : 0,
      "timeIndexingWithoutContentViaInfrastructureExtension" : 0,
      "roots" : [ ]
    }, {
      "providerName" : "Library Gradle: androidx.coordinatorlayout:coordinatorlayout:1.1.0@aar (#3 class roots, #1 source roots)",
      "numberOfScannedFiles" : 21,
      "numberOfSkippedFiles" : 0,
      "numberOfFilesForIndexing" : 0,
      "numberOfFilesFullyIndexedByInfrastructureExtensions" : 0,
      "filesFullyIndexedByInfrastructureExtensions" : [ ],
      "statusTime" : 11900,
      "totalOneThreadTimeWithPauses" : 680300,
      "iterationAndScannersApplicationTime" : 496000,
      "filesCheckTime" : 89200,
      "timeProcessingUpToDateFiles" : 0,
      "timeUpdatingContentLessIndexes" : 0,
      "timeIndexingWithoutContentViaInfrastructureExtension" : 0,
      "roots" : [ ]
    }, {
      "providerName" : "Library Gradle: org.hamcrest:hamcrest-integration:1.3 (#1 class roots, #1 source roots)",
      "numberOfScannedFiles" : 13,
      "numberOfSkippedFiles" : 0,
      "numberOfFilesForIndexing" : 0,
      "numberOfFilesFullyIndexedByInfrastructureExtensions" : 0,
      "filesFullyIndexedByInfrastructureExtensions" : [ ],
      "statusTime" : 4900,
      "totalOneThreadTimeWithPauses" : 643600,
      "iterationAndScannersApplicationTime" : 465300,
      "filesCheckTime" : 96800,
      "timeProcessingUpToDateFiles" : 0,
      "timeUpdatingContentLessIndexes" : 0,
      "timeIndexingWithoutContentViaInfrastructureExtension" : 0,
      "roots" : [ ]
    }, {
      "providerName" : "Library Gradle: com.google.firebase:firebase-appcheck-interop:17.0.0@aar (#2 class roots, #1 source roots)",
      "numberOfScannedFiles" : 10,
      "numberOfSkippedFiles" : 0,
      "numberOfFilesForIndexing" : 0,
      "numberOfFilesFullyIndexedByInfrastructureExtensions" : 0,
      "filesFullyIndexedByInfrastructureExtensions" : [ ],
      "statusTime" : 5200,
      "totalOneThreadTimeWithPauses" : 639700,
      "iterationAndScannersApplicationTime" : 495700,
      "filesCheckTime" : 64600,
      "timeProcessingUpToDateFiles" : 0,
      "timeUpdatingContentLessIndexes" : 0,
      "timeIndexingWithoutContentViaInfrastructureExtension" : 0,
      "roots" : [ ]
    }, {
      "providerName" : "Library Gradle: androidx.documentfile:documentfile:1.0.0@aar (#2 class roots, #1 source roots)",
      "numberOfScannedFiles" : 13,
      "numberOfSkippedFiles" : 0,
      "numberOfFilesForIndexing" : 0,
      "numberOfFilesFullyIndexedByInfrastructureExtensions" : 0,
      "filesFullyIndexedByInfrastructureExtensions" : [ ],
      "statusTime" : 11100,
      "totalOneThreadTimeWithPauses" : 621700,
      "iterationAndScannersApplicationTime" : 438500,
      "filesCheckTime" : 95300,
      "timeProcessingUpToDateFiles" : 0,
      "timeUpdatingContentLessIndexes" : 0,
      "timeIndexingWithoutContentViaInfrastructureExtension" : 0,
      "roots" : [ ]
    }, {
      "providerName" : "Library Gradle: androidx.interpolator:interpolator:1.0.0@aar (#2 class roots, #1 source roots)",
      "numberOfScannedFiles" : 11,
      "numberOfSkippedFiles" : 0,
      "numberOfFilesForIndexing" : 0,
      "numberOfFilesFullyIndexedByInfrastructureExtensions" : 0,
      "filesFullyIndexedByInfrastructureExtensions" : [ ],
      "statusTime" : 7200,
      "totalOneThreadTimeWithPauses" : 600300,
      "iterationAndScannersApplicationTime" : 368400,
      "filesCheckTime" : 154100,
      "timeProcessingUpToDateFiles" : 0,
      "timeUpdatingContentLessIndexes" : 0,
      "timeIndexingWithoutContentViaInfrastructureExtension" : 0,
      "roots" : [ ]
    }, {
      "providerName" : "Library Gradle: androidx.vectordrawable:vectordrawable:1.1.0@aar (#2 class roots, #1 source roots)",
      "numberOfScannedFiles" : 18,
      "numberOfSkippedFiles" : 0,
      "numberOfFilesForIndexing" : 0,
      "numberOfFilesFullyIndexedByInfrastructureExtensions" : 0,
      "filesFullyIndexedByInfrastructureExtensions" : [ ],
      "statusTime" : 7100,
      "totalOneThreadTimeWithPauses" : 579600,
      "iterationAndScannersApplicationTime" : 450000,
      "filesCheckTime" : 55200,
      "timeProcessingUpToDateFiles" : 0,
      "timeUpdatingContentLessIndexes" : 0,
      "timeIndexingWithoutContentViaInfrastructureExtension" : 0,
      "roots" : [ ]
    }, {
      "providerName" : "Library Gradle: androidx.localbroadcastmanager:localbroadcastmanager:1.0.0@aar (#2 class roots, #1 source roots)",
      "numberOfScannedFiles" : 8,
      "numberOfSkippedFiles" : 0,
      "numberOfFilesForIndexing" : 0,
      "numberOfFilesFullyIndexedByInfrastructureExtensions" : 0,
      "filesFullyIndexedByInfrastructureExtensions" : [ ],
      "statusTime" : 18000,
      "totalOneThreadTimeWithPauses" : 572400,
      "iterationAndScannersApplicationTime" : 380100,
      "filesCheckTime" : 92100,
      "timeProcessingUpToDateFiles" : 0,
      "timeUpdatingContentLessIndexes" : 0,
      "timeIndexingWithoutContentViaInfrastructureExtension" : 0,
      "roots" : [ ]
    }, {
      "providerName" : "Library Gradle: javax.inject:javax.inject:1 (#1 class roots, #1 source roots)",
      "numberOfScannedFiles" : 13,
      "numberOfSkippedFiles" : 0,
      "numberOfFilesForIndexing" : 0,
      "numberOfFilesFullyIndexedByInfrastructureExtensions" : 0,
      "filesFullyIndexedByInfrastructureExtensions" : [ ],
      "statusTime" : 4700,
      "totalOneThreadTimeWithPauses" : 564900,
      "iterationAndScannersApplicationTime" : 377100,
      "filesCheckTime" : 77800,
      "timeProcessingUpToDateFiles" : 0,
      "timeUpdatingContentLessIndexes" : 0,
      "timeIndexingWithoutContentViaInfrastructureExtension" : 0,
      "roots" : [ ]
    }, {
      "providerName" : "Library Gradle: androidx.arch.core:core-runtime:2.1.0@aar (#2 class roots, #1 source roots)",
      "numberOfScannedFiles" : 12,
      "numberOfSkippedFiles" : 0,
      "numberOfFilesForIndexing" : 0,
      "numberOfFilesFullyIndexedByInfrastructureExtensions" : 0,
      "filesFullyIndexedByInfrastructureExtensions" : [ ],
      "statusTime" : 4600,
      "totalOneThreadTimeWithPauses" : 560800,
      "iterationAndScannersApplicationTime" : 461500,
      "filesCheckTime" : 42700,
      "timeProcessingUpToDateFiles" : 0,
      "timeUpdatingContentLessIndexes" : 0,
      "timeIndexingWithoutContentViaInfrastructureExtension" : 0,
      "roots" : [ ]
    }, {
      "providerName" : "Library Gradle: androidx.lifecycle:lifecycle-runtime:2.5.0@aar (#3 class roots, #1 source roots)",
      "numberOfScannedFiles" : 15,
      "numberOfSkippedFiles" : 0,
      "numberOfFilesForIndexing" : 0,
      "numberOfFilesFullyIndexedByInfrastructureExtensions" : 0,
      "filesFullyIndexedByInfrastructureExtensions" : [ ],
      "statusTime" : 15000,
      "totalOneThreadTimeWithPauses" : 545200,
      "iterationAndScannersApplicationTime" : 390200,
      "filesCheckTime" : 77500,
      "timeProcessingUpToDateFiles" : 0,
      "timeUpdatingContentLessIndexes" : 0,
      "timeIndexingWithoutContentViaInfrastructureExtension" : 0,
      "roots" : [ ]
    }, {
      "providerName" : "Library Gradle: com.google.firebase:firebase-annotations:16.2.0 (#1 class roots, #0 source roots)",
      "numberOfScannedFiles" : 8,
      "numberOfSkippedFiles" : 0,
      "numberOfFilesForIndexing" : 0,
      "numberOfFilesFullyIndexedByInfrastructureExtensions" : 0,
      "filesFullyIndexedByInfrastructureExtensions" : [ ],
      "statusTime" : 5400,
      "totalOneThreadTimeWithPauses" : 526700,
      "iterationAndScannersApplicationTime" : 366100,
      "filesCheckTime" : 77700,
      "timeProcessingUpToDateFiles" : 0,
      "timeUpdatingContentLessIndexes" : 0,
      "timeIndexingWithoutContentViaInfrastructureExtension" : 0,
      "roots" : [ ]
    }, {
      "providerName" : "Library Gradle: com.squareup:javawriter:2.1.1 (#1 class roots, #1 source roots)",
      "numberOfScannedFiles" : 7,
      "numberOfSkippedFiles" : 0,
      "numberOfFilesForIndexing" : 0,
      "numberOfFilesFullyIndexedByInfrastructureExtensions" : 0,
      "filesFullyIndexedByInfrastructureExtensions" : [ ],
      "statusTime" : 2600,
      "totalOneThreadTimeWithPauses" : 502400,
      "iterationAndScannersApplicationTime" : 350700,
      "filesCheckTime" : 72700,
      "timeProcessingUpToDateFiles" : 0,
      "timeUpdatingContentLessIndexes" : 0,
      "timeIndexingWithoutContentViaInfrastructureExtension" : 0,
      "roots" : [ ]
    }, {
      "providerName" : "Library Gradle: com.google.firebase:firebase-measurement-connector:19.0.0@aar (#2 class roots, #0 source roots)",
      "numberOfScannedFiles" : 7,
      "numberOfSkippedFiles" : 0,
      "numberOfFilesForIndexing" : 0,
      "numberOfFilesFullyIndexedByInfrastructureExtensions" : 0,
      "filesFullyIndexedByInfrastructureExtensions" : [ ],
      "statusTime" : 10300,
      "totalOneThreadTimeWithPauses" : 482500,
      "iterationAndScannersApplicationTime" : 322600,
      "filesCheckTime" : 72500,
      "timeProcessingUpToDateFiles" : 0,
      "timeUpdatingContentLessIndexes" : 0,
      "timeIndexingWithoutContentViaInfrastructureExtension" : 0,
      "roots" : [ ]
    }, {
      "providerName" : "Library Gradle: androidx.test.espresso:espresso-idling-resource:3.4.0@aar (#2 class roots, #1 source roots)",
      "numberOfScannedFiles" : 9,
      "numberOfSkippedFiles" : 0,
      "numberOfFilesForIndexing" : 0,
      "numberOfFilesFullyIndexedByInfrastructureExtensions" : 0,
      "filesFullyIndexedByInfrastructureExtensions" : [ ],
      "statusTime" : 9400,
      "totalOneThreadTimeWithPauses" : 481200,
      "iterationAndScannersApplicationTime" : 357100,
      "filesCheckTime" : 58800,
      "timeProcessingUpToDateFiles" : 0,
      "timeUpdatingContentLessIndexes" : 0,
      "timeIndexingWithoutContentViaInfrastructureExtension" : 0,
      "roots" : [ ]
    }, {
      "providerName" : "Library Gradle: com.google.firebase:firebase-auth-interop:20.0.0@aar (#2 class roots, #0 source roots)",
      "numberOfScannedFiles" : 10,
      "numberOfSkippedFiles" : 0,
      "numberOfFilesForIndexing" : 0,
      "numberOfFilesFullyIndexedByInfrastructureExtensions" : 0,
      "filesFullyIndexedByInfrastructureExtensions" : [ ],
      "statusTime" : 6200,
      "totalOneThreadTimeWithPauses" : 480700,
      "iterationAndScannersApplicationTime" : 324200,
      "filesCheckTime" : 79000,
      "timeProcessingUpToDateFiles" : 0,
      "timeUpdatingContentLessIndexes" : 0,
      "timeIndexingWithoutContentViaInfrastructureExtension" : 0,
      "roots" : [ ]
    }, {
      "providerName" : "Library Gradle: androidx.lifecycle:lifecycle-livedata:2.0.0@aar (#2 class roots, #1 source roots)",
      "numberOfScannedFiles" : 16,
      "numberOfSkippedFiles" : 0,
      "numberOfFilesForIndexing" : 0,
      "numberOfFilesFullyIndexedByInfrastructureExtensions" : 0,
      "filesFullyIndexedByInfrastructureExtensions" : [ ],
      "statusTime" : 11400,
      "totalOneThreadTimeWithPauses" : 474400,
      "iterationAndScannersApplicationTime" : 340600,
      "filesCheckTime" : 62800,
      "timeProcessingUpToDateFiles" : 0,
      "timeUpdatingContentLessIndexes" : 0,
      "timeIndexingWithoutContentViaInfrastructureExtension" : 0,
      "roots" : [ ]
    }, {
      "providerName" : "Library Gradle: org.jetbrains.kotlin:kotlin-stdlib-jdk8:1.8.22 (#1 class roots, #1 source roots)",
      "numberOfScannedFiles" : 4,
      "numberOfSkippedFiles" : 0,
      "numberOfFilesForIndexing" : 0,
      "numberOfFilesFullyIndexedByInfrastructureExtensions" : 0,
      "filesFullyIndexedByInfrastructureExtensions" : [ ],
      "statusTime" : 6200,
      "totalOneThreadTimeWithPauses" : 442700,
      "iterationAndScannersApplicationTime" : 326500,
      "filesCheckTime" : 53900,
      "timeProcessingUpToDateFiles" : 0,
      "timeUpdatingContentLessIndexes" : 0,
      "timeIndexingWithoutContentViaInfrastructureExtension" : 0,
      "roots" : [ ]
    }, {
      "providerName" : "Library Gradle: org.jetbrains.kotlinx:kotlinx-coroutines-play-services:1.7.3 (#1 class roots, #1 source roots)",
      "numberOfScannedFiles" : 12,
      "numberOfSkippedFiles" : 0,
      "numberOfFilesForIndexing" : 0,
      "numberOfFilesFullyIndexedByInfrastructureExtensions" : 0,
      "filesFullyIndexedByInfrastructureExtensions" : [ ],
      "statusTime" : 8700,
      "totalOneThreadTimeWithPauses" : 429600,
      "iterationAndScannersApplicationTime" : 315600,
      "filesCheckTime" : 54200,
      "timeProcessingUpToDateFiles" : 0,
      "timeUpdatingContentLessIndexes" : 0,
      "timeIndexingWithoutContentViaInfrastructureExtension" : 0,
      "roots" : [ ]
    }, {
      "providerName" : "Indexable set contributor 'org.jetbrains.kotlin.idea.base.indices.contributors.BuiltInsIndexableSetContributor@71cc387a' (project)",
      "numberOfScannedFiles" : 0,
      "numberOfSkippedFiles" : 0,
      "numberOfFilesForIndexing" : 0,
      "numberOfFilesFullyIndexedByInfrastructureExtensions" : 0,
      "filesFullyIndexedByInfrastructureExtensions" : [ ],
      "statusTime" : 0,
      "totalOneThreadTimeWithPauses" : 377400,
      "iterationAndScannersApplicationTime" : 25500,
      "filesCheckTime" : 293800,
      "timeProcessingUpToDateFiles" : 0,
      "timeUpdatingContentLessIndexes" : 0,
      "timeIndexingWithoutContentViaInfrastructureExtension" : 0,
      "roots" : [ ]
    }, {
      "providerName" : "Library Gradle: com.google.guava:listenablefuture:9999.0-empty-to-avoid-conflict-with-guava (#1 class roots, #0 source roots)",
      "numberOfScannedFiles" : 3,
      "numberOfSkippedFiles" : 0,
      "numberOfFilesForIndexing" : 0,
      "numberOfFilesFullyIndexedByInfrastructureExtensions" : 0,
      "filesFullyIndexedByInfrastructureExtensions" : [ ],
      "statusTime" : 1600,
      "totalOneThreadTimeWithPauses" : 362300,
      "iterationAndScannersApplicationTime" : 209500,
      "filesCheckTime" : 67400,
      "timeProcessingUpToDateFiles" : 0,
      "timeUpdatingContentLessIndexes" : 0,
      "timeIndexingWithoutContentViaInfrastructureExtension" : 0,
      "roots" : [ ]
    }, {
      "providerName" : "Library Gradle: org.jetbrains.kotlin:kotlin-stdlib-jdk7:1.8.22 (#1 class roots, #1 source roots)",
      "numberOfScannedFiles" : 4,
      "numberOfSkippedFiles" : 0,
      "numberOfFilesForIndexing" : 0,
      "numberOfFilesFullyIndexedByInfrastructureExtensions" : 0,
      "filesFullyIndexedByInfrastructureExtensions" : [ ],
      "statusTime" : 2500,
      "totalOneThreadTimeWithPauses" : 350000,
      "iterationAndScannersApplicationTime" : 216300,
      "filesCheckTime" : 51800,
      "timeProcessingUpToDateFiles" : 0,
      "timeUpdatingContentLessIndexes" : 0,
      "timeIndexingWithoutContentViaInfrastructureExtension" : 0,
      "roots" : [ ]
    }, {
      "providerName" : "Custom kind roots from entity (scratches, empty)",
      "numberOfScannedFiles" : 2,
      "numberOfSkippedFiles" : 0,
      "numberOfFilesForIndexing" : 0,
      "numberOfFilesFullyIndexedByInfrastructureExtensions" : 0,
      "filesFullyIndexedByInfrastructureExtensions" : [ ],
      "statusTime" : 1600,
      "totalOneThreadTimeWithPauses" : 349100,
      "iterationAndScannersApplicationTime" : 124200,
      "filesCheckTime" : 92700,
      "timeProcessingUpToDateFiles" : 0,
      "timeUpdatingContentLessIndexes" : 0,
      "timeIndexingWithoutContentViaInfrastructureExtension" : 0,
      "roots" : [ ]
    }, {
      "providerName" : "Library Gradle: com.google.firebase:firebase-analytics:22.0.1@aar (#2 class roots, #0 source roots)",
      "numberOfScannedFiles" : 3,
      "numberOfSkippedFiles" : 0,
      "numberOfFilesForIndexing" : 0,
      "numberOfFilesFullyIndexedByInfrastructureExtensions" : 0,
      "filesFullyIndexedByInfrastructureExtensions" : [ ],
      "statusTime" : 1500,
      "totalOneThreadTimeWithPauses" : 278100,
      "iterationAndScannersApplicationTime" : 150400,
      "filesCheckTime" : 54700,
      "timeProcessingUpToDateFiles" : 0,
      "timeUpdatingContentLessIndexes" : 0,
      "timeIndexingWithoutContentViaInfrastructureExtension" : 0,
      "roots" : [ ]
    }, {
      "providerName" : "Indexable set contributor 'Version Catalogs' (project)",
      "numberOfScannedFiles" : 0,
      "numberOfSkippedFiles" : 1,
      "numberOfFilesForIndexing" : 0,
      "numberOfFilesFullyIndexedByInfrastructureExtensions" : 0,
      "filesFullyIndexedByInfrastructureExtensions" : [ ],
      "statusTime" : 0,
      "totalOneThreadTimeWithPauses" : 194500,
      "iterationAndScannersApplicationTime" : 80300,
      "filesCheckTime" : 59500,
      "timeProcessingUpToDateFiles" : 0,
      "timeUpdatingContentLessIndexes" : 0,
      "timeIndexingWithoutContentViaInfrastructureExtension" : 0,
      "roots" : [ ]
    }, {
      "providerName" : "Indexable set contributor 'Scratches & Consoles' (project)",
      "numberOfScannedFiles" : 0,
      "numberOfSkippedFiles" : 0,
      "numberOfFilesForIndexing" : 0,
      "numberOfFilesFullyIndexedByInfrastructureExtensions" : 0,
      "filesFullyIndexedByInfrastructureExtensions" : [ ],
      "statusTime" : 0,
      "totalOneThreadTimeWithPauses" : 193600,
      "iterationAndScannersApplicationTime" : 72700,
      "filesCheckTime" : 40800,
      "timeProcessingUpToDateFiles" : 0,
      "timeUpdatingContentLessIndexes" : 0,
      "timeIndexingWithoutContentViaInfrastructureExtension" : 0,
      "roots" : [ ]
    }, {
      "providerName" : "Indexable set contributor 'Scratches & Consoles' (non-project)",
      "numberOfScannedFiles" : 0,
      "numberOfSkippedFiles" : 0,
      "numberOfFilesForIndexing" : 0,
      "numberOfFilesFullyIndexedByInfrastructureExtensions" : 0,
      "filesFullyIndexedByInfrastructureExtensions" : [ ],
      "statusTime" : 0,
      "totalOneThreadTimeWithPauses" : 100800,
      "iterationAndScannersApplicationTime" : 20100,
      "filesCheckTime" : 32600,
      "timeProcessingUpToDateFiles" : 0,
      "timeUpdatingContentLessIndexes" : 0,
      "timeIndexingWithoutContentViaInfrastructureExtension" : 0,
      "roots" : [ ]
    }, {
      "providerName" : "Indexable set contributor 'com.intellij.javaee.ExternalResourcesRootsProvider@3fbf254a' (project)",
      "numberOfScannedFiles" : 0,
      "numberOfSkippedFiles" : 0,
      "numberOfFilesForIndexing" : 0,
      "numberOfFilesFullyIndexedByInfrastructureExtensions" : 0,
      "filesFullyIndexedByInfrastructureExtensions" : [ ],
      "statusTime" : 0,
      "totalOneThreadTimeWithPauses" : 79900,
      "iterationAndScannersApplicationTime" : 14300,
      "filesCheckTime" : 23100,
      "timeProcessingUpToDateFiles" : 0,
      "timeUpdatingContentLessIndexes" : 0,
      "timeIndexingWithoutContentViaInfrastructureExtension" : 0,
      "roots" : [ ]
    }, {
      "providerName" : "Indexable set contributor 'Version Catalogs' (non-project)",
      "numberOfScannedFiles" : 0,
      "numberOfSkippedFiles" : 0,
      "numberOfFilesForIndexing" : 0,
      "numberOfFilesFullyIndexedByInfrastructureExtensions" : 0,
      "filesFullyIndexedByInfrastructureExtensions" : [ ],
      "statusTime" : 0,
      "totalOneThreadTimeWithPauses" : 76200,
      "iterationAndScannersApplicationTime" : 16800,
      "filesCheckTime" : 28000,
      "timeProcessingUpToDateFiles" : 0,
      "timeUpdatingContentLessIndexes" : 0,
      "timeIndexingWithoutContentViaInfrastructureExtension" : 0,
      "roots" : [ ]
    } ]
  }
}